Workbook
Name ActivosTotales: Cálculos!$B$9
Name Imprimir_Área: [1]Dashboard!$A$1:$H$19
Name PasivosTotales: tblNoAsegurado[[#Totals],[Tope]]
Name PatrimonioNeto: Cálculos!$B$9

Sheet 2026
A1: NºPer. | B1: DNI | C1: Nombre | D1: Desde* | E1: Hasta* | F1: NºProp. | G1: Nombrto/Contrato | H1: Razón de Alta | I1: Plaza | J1: RJ | K1: Cláusula | L1: T.Nombrto | M1: Días | N1: Puesto trabajo | O1: GFH | P1: Dirección | Q1: NºPer.Sust | R1: DNI.Sust | S1: Nombre Sustituido | T1: Puesto Sustitutido | U1: Hasta*Usada | V1: F_Necesidad | W1: Necesidad
A2: 160888 | B2: 43832660L | C2: LEON GONZALEZ, PATRICIA | D2: 46023 | E2: 46033 | F2: 169690 | G2: TEMPORAL. T. COM. INTER. N. ESTA | H2: INTERINO POR VACANTE | I2: FEA ENDOCRINOLOGÍA Y N | J2: E | K2: I_9_1a | L2: N91a | M2: 11 | N2: FEA ENDOCRINOLOGÍA Y NUTRICIÓN | O2: P.MÉDICO ENDOCRINOLOGÍA | P2: DIRECCIÓN MÉDICA | Q2: 0 | U2: 46033
A3: 187533 | B3: 45456485K | C3: MASCAREÑO PEREZ, MARIA ISABEL | D3: 46023 | E3: 46033 | F3: 153022 | G3: TEMPORAL. T. COM. INTER. N. ESTA | H3: INTERINO POR VACANTE | I3: MEDICO/A URGENCIA HOSPITALARIA | J3: E | K3: I_9_1a | L3: N91a | M3: 11 | N3: MÉDICO URGENCIA HOSPITALARIA | O3: P.MÉDICO GERIATRÍA HOSP.NORTE | P3: DIRECCIÓN MÉDICA | Q3: 0 | U3: 46033
A4: 236228 | B4: 78646939A | C4: REYES GONZALEZ CASANOVA, PAULA | D4: 46023 | E4: 46033 | F4: 169694 | G4: TEMPORAL. T. COM. INTER. N. ESTA | H4: INTERINO POR VACANTE | I4: FEA HEMATOLOGÍA Y HEMOTERAPIA | J4: E | K4: I_9_1a | L4: N91a | M4: 11 | N4: FEA HEMATOLOGIA Y HEMOTERAPIA | O4: P.MÉDICO HEMATOLOGÍA CLÍNICA | P4: DIRECCIÓN MÉDICA | Q4: 0 | U4: 46033
A5: 225280 | B5: 78717263Q | C5: TOSCO NUÑEZ, TOMAS | D5: 46023 | E5: 46033 | F5: 169702 | G5: TEMPORAL. T. COM. INTER. N. ESTA | H5: INTERINO POR VACANTE | I5: FEA MICROBIOLOGÍA Y PARASITOLOGÍA | J5: E | K5: I_9_1a | L5: N91a | M5: 11 | N5: FEA MICROBIOLOGÍA Y PARASITOLOGÍA | O5: P.MÉDICO MICROBIOLOGÍA Y CONTROL INFECCI | P5: DIRECCIÓN MÉDICA | Q5: 0 | U5: 46033
A6: 349426 | B6: 77147626Z | C6: BAEZA RUIZ, ADRIAN | D6: 46023 | E6: 46033 | F6: 169719 | G6: TEMPORAL. T. COM. INTER. N. ESTA | H6: INTERINO POR VACANTE | I6: FEA NEUMOLOGÍA | J6: E | K6: I_9_1a | L6: N91a | M6: 11 | N6: FEA NEUMOLOGÍA | O6: P.MÉDICO NEUMOLOGÍA | P6: DIRECCIÓN MÉDICA | Q6: 0 | U6: 46033
A7: 389597 | B7: 78724201P | C7: HERNANDEZ GARCIA, VERONICA SARAY | D7: 46023 | E7: 46033 | F7: 152987 | G7: TEMPORAL. T. COM. INTER. N. ESTA | H7: INTERINO POR VACANTE | I7: FEA NEUMOLOGÍA | J7: E | K7: I_9_1a | L7: N91a | M7: 11 | N7: FEA NEUMOLOGÍA | O7: P.MÉDICO NEUMOLOGÍA | P7: DIRECCIÓN MÉDICA | Q7: 0 | U7: 46033
A8: 229588 | B8: 78642879Z | C8: MESA LEON, NELSON | D8: 46023 | E8: 46033 | F8: 169720 | G8: TEMPORAL. T. COM. INTER. N. ESTA | H8: INTERINO POR VACANTE | I8: FEA NEUMOLOGÍA | J8: E | K8: I_9_1a | L8: N91a | M8: 11 | N8: FEA NEUMOLOGÍA | O8: P.MÉDICO NEUMOLOGÍA | P8: DIRECCIÓN MÉDICA | Q8: 0 | U8: 46033
A9: 399975 | B9: 72894206F | C9: ESCALADA PELLITERO, SILVIA | D9: 46023 | E9: 46035 | F9: 153000 | G9: TEMPORAL. T. COM. INTER. N. ESTA | H9: INTERINO POR VACANTE | I9: FEA PEDIATRÍA | J9: E | K9: I_9_1a | L9: N91a | M9: 13 | N9: FEA PEDIATRÍA | O9: P.MÉDICO PEDIATRÍA | P9: DIRECCIÓN MÉDICA | Q9: 0 | U9: 46035
A10: 378335 | B10: 51148047A | C10: PEREZ DE ARMAS, PAULA | D10: 46023 | E10: 46037 | F10: 169718 | G10: TEMPORAL. T. COM. INTER. N. ESTA | H10: INTERINO POR VACANTE | I10: FEA NEUMOLOGÍA | J10: E | K10: I_9_1a | L10: N91a | M10: 15 | N10: FEA NEUMOLOGÍA | O10: P.MÉDICO NEUMOLOGÍA | P10: DIRECCIÓN MÉDICA | Q10: 0 | U10: 46037
A11: 211865 | B11: 54112637P | C11: ALFONSO ALVAREZ, MARTA | D11: 46023 | E11: 46043 | F11: 155903 | G11: TEMPORAL. T. COM. INTER. N. ESTA | H11: INTERINO POR VACANTE | I11: TÉC ESPECIALISTA / RADIODIAGNÓSTICO | J11: E | K11: I_9_1a | L11: N91a | M11: 21 | N11: TÉCNICO ESPECIALISTA RADIODIAGNÓSTICO | O11: AREA.ENFERMERIA - CAE LA LAGUNA-GENETO | P11: DIRECCIÓN DE ENFERMERÍA | Q11: 0 | U11: 46043
A12: 218739 | B12: 78725868L | C12: RODRIGUEZ GONZALEZ, DARA | D12: 46023 | E12: 46048 | F12: 0 | G12: TEMPORAL. T. COM. INTER. N. ESTA | H12: INTERINO POR VACANTE | I12: FEA BIOQUÍMICA CLÍNICA | J12: E | K12: I_9_1a | L12: N91a | M12: 26 | N12: FEA BIOQUÍMICA CLÍNICA | O12: P.MÉDICO FISIOLOGÍA Y BIOQUÍMICA | P12: DIRECCIÓN MÉDICA | Q12: 0 | U12: 46048
A13: 359613 | B13: 70253317R | C13: MUÑOZ TORRERO MARTIN, ANA | D13: 46023 | E13: 46053 | F13: 170603 | G13: TEMPORAL. T. COM. INTER. N. ESTA | H13: INTERINO POR VACANTE | I13: ENFERMERO/A | J13: E | K13: I_9_1a | L13: N91a | M13: 31 | N13: ENFERMERA/O | O13: UDAD.DE RECUPERACIÓN DE QUIRÓFANO | P13: DIRECCIÓN DE ENFERMERÍA | Q13: 0 | U13: 46053
... A89: 219892 | B89: 43356801F | C89: MOLINA GONZALEZ, DELFINA | D89: 46023 | E89: 46146 | F89: 169789 | G89: TEMPORAL. T. COM. INTER. N. ESTA | H89: INTERINO POR VACANTE | I89: TÉC ESPECIALISTA / LABORATORIO | J89: E | K89: I_9_1a | L89: N91a | M89: 124 | N89: TÉCNICO ESPECIALISTA LABORATORIO | O89: LABORATORIO CENTRAL | P89: DIRECCIÓN DE ENFERMERÍA | Q89: 0 | U89: 46146
A90: 332898 | B90: 45443450G | C90: ROSA GONZALEZ, MARIA TERESA.DE.LA. | D90: 46023 | E90: 46146 | F90: 154032 | G90: TEMPORAL. T. COM. INTER. N. ESTA | H90: INTERINO POR VACANTE | I90: TÉC ESPECIALISTA / RADIODIAGNÓSTICO | J90: E | K90: I_9_1a | L90: N91a | M90: 124 | N90: TÉCNICO ESPECIALISTA RADIODIAGNÓSTICO | O90: RADIODIAGNOSTICO | P90: DIRECCIÓN DE ENFERMERÍA | Q90: 0 | U90: 46146 | V90: 46387 | W90: =_xlfn.DAYS(V90,U90) -> 241
A91: 236495 | B91: 09290030P | C91: HORTELANO HORTELANO, CELIA | D91: 46023 | E91: 46147 | F91: 162706 | G91: TEMPORAL. T. COM. INTER. N. ESTA | H91: INTERINO POR VACANTE | I91: FEA PSICOLOGÍA CLÍNICA | J91: E | K91: I_9_1a | L91: N91a | M91: 125 | N91: FEA PSICOLOGÍA CLÍNICA | O91: P.MÉDICO PSIQUIATRÍA | P91: DIRECCIÓN MÉDICA | Q91: 0 | U91: 46147
A92: 223768 | B92: 78722483S | C92: ARMAS RODRIGUEZ, INGRID | D92: 46023 | E92: 46152 | F92: 161163 | G92: TEMPORAL. T. COM. INTER. N. ESTA | H92: INTERINO POR VACANTE | I92: AUXILIAR DE ENFERMERÍA | J92: E | K92: I_9_1a | L92: N91a | M92: 130 | N92: AUXILIAR DE ENFERMERÍA | O92: URGENCIAS | P92: DIRECCIÓN DE ENFERMERÍA | Q92: 0 | U92: 46152
A93: 229557 | B93: 43832509Y | C93: FAJARDO RODRIGUEZ, DIEGO | D93: 46113 | E93: 46154 | F93: 177708 | G93: TEMPORAL. T. COM. INTER. N. ESTA | H93: INTERINO POR VACANTE | I93: COCINERO/A | J93: E | K93: I_9_1a | L93: N91a | M93: 42 | N93: COCINERO | O93: COCINA | P93: Dirección Servicios Generales | Q93: 0 | U93: 46154
A94: 238495 | B94: 43821391C | C94: PADRON CAMPOS, BEATRIZ | D94: 46023 | E94: 46156 | F94: 161545 | G94: TEMPORAL. T. COM. INTER. N. ESTA | H94: INTERINO POR VACANTE | I94: TÉCNICA/O AUXILIAR DE FARMACIA | J94: E | K94: I_9_1a | L94: N91a | M94: 134 | N94: TÉCNICA/O AUXILIAR DE FARMACIA | O94: ALMACÉN DE FARMACIA | P94: DIRECCIÓN DE ENFERMERÍA | Q94: 0 | U94: 46156
A95: 340820 | B95: 42057023M | C95: HERNANDEZ RODRIGUEZ, JOSE FRANCISCO | D95: 46023 | E95: 46161 | F95: 162751 | G95: TEMPORAL. T. COM. INTER. N. ESTA | H95: INTERINO POR VACANTE | I95: G ADMINISTRATIVO FUNCIÓN ADMINISTRATIVA | J95: E | K95: I_9_1a | L95: N91a | M95: 139 | N95: GRUPO ADMINISTRATIVO | O95: RECEPCIÓN DE POLICLÍNICA | P95: Dirección Planificación y Gestión RREE | Q95: 0 | U95: 46161
A96: 311640 | B96: 42077016B | C96: DELGADO SANTANA, MARIA NIEVES | D96: 46023 | E96: 46162 | F96: 149704 | G96: TEMPORAL. T. COM. INTER. N. ESTA | H96: INTERINO POR VACANTE | I96: G ADMINISTRATIVO FUNCIÓN ADMINISTRATIVA | J96: E | K96: I_9_1a | L96: N91a | M96: 140 | N96: GRUPO ADMINISTRATIVO | O96: COORDINACIÓN DE INFORMACIÓN | P96: GERENCIA | Q96: 0 | U96: 46162
A97: 284301 | B97: 43608597E | C97: SANCHEZ GUTIERREZ, DOMINGO | D97: 46023 | E97: 46165 | F97: 162756 | G97: TEMPORAL. T. COM. INTER. N. ESTA | H97: INTERINO POR VACANTE | I97: G ADMINISTRATIVO FUNCIÓN ADMINISTRATIVA | J97: E | K97: I_9_1a | L97: N91a | M97: 143 | N97: GRUPO ADMINISTRATIVO | O97: ADMISIÓN URGENCIAS | P97: DIRECCIÓN MÉDICA | Q97: 0 | U97: 46165
A98: 309724 | B98: 76883227T | C98: RAYA DURAN, MARIA | D98: 46023 | E98: 46173 | F98: 170581 | G98: TEMPORAL. T. COM. INTER. N. ESTA | H98: INTERINO POR VACANTE | I98: ENFERMERO/A | J98: E | K98: I_9_1a | L98: N91a | M98: 151 | N98: ENFERMERA/O | O98: PLANTA 2ª - HOSPITALIZACIÓN EDIF. D | P98: DIRECCIÓN DE ENFERMERÍA | Q98: 0 | U98: 46173
A99: 217287 | B99: 60685293T | C99: BRAVO LJUBETIC, LUCIANO ANDRES | D99: 46023 | E99: 46173 | F99: 150183 | G99: TEMPORAL. T. COM. INTER. N. ESTA | H99: INTERINO POR VACANTE | I99: FEA OFTALMOLOGÍA | J99: E | K99: I_9_1a | L99: N91a | M99: 151 | N99: FEA OFTALMOLOGÍA | O99: P.MÉDICO OFTALMOLOGÍA | P99: DIRECCIÓN MÉDICA | Q99: 0 | U99: 46173
A100: 250120 | B100: 78720481Z | C100: LARRAÑAGA FRAGOSO, PAULA CRISTINA | D100: 46023 | E100: 46173 | F100: 143101 | G100: TEMPORAL. T. COM. INTER. N. ESTA | H100: INTERINO POR VACANTE | I100: FEA OFTALMOLOGÍA | J100: E | K100: I_9_1a | L100: N91a | M100: 151 | N100: FEA OFTALMOLOGÍA | O100: P.MÉDICO OFTALMOLOGÍA | P100: DIRECCIÓN MÉDICA | Q100: 0 | U100: 46173
A101: 378965 | B101: 76262742D | C101: AYUSO SANCHEZ, CELIA | D101: 46023 | E101: 46181 | F101: 170729 | G101: TEMPORAL. T. COM. INTER. N. ESTA | H101: INTERINO POR VACANTE | I101: ENFERMERO/A | J101: E | K101: I_9_1a | L101: N91a | M101: 159 | N101: ENFERMERA/O | O101: URGENCIAS | P101: DIRECCIÓN DE ENFERMERÍA | Q101: 0 | U101: 46181
A102: 253583 | B102: 78699024Q | C102: FERNANDEZ ALVAREZ, PAULA | D102: 46023 | E102: 46187 | F102: 0 | G102: TEMPORAL. T. COM. INTER. N. ESTA | H102: INTERINO POR VACANTE | I102: TÉCNICO/A TITULADO/A MEDIO | J102: E | K102: I_9_1a | L102: N91a | M102: 165 | N102: PERSONAL TÉCNICO (G.MEDIO) | O102: CONSULTA OFTALMOLOGÍA | P102: DIRECCIÓN DE ENFERMERÍA | Q102: 0 | U102: 46187
... A822: 270579 | B822: 78630221Y | C822: HERNANDEZ MESA, NAYRA | D822: 46023 | E822: 46387 | F822: 161119 | G822: TEMPORAL. T. COM. INTER. N. ESTA | H822: INTERINO POR VACANTE | I822: AUXILIAR DE ENFERMERÍA | J822: E | K822: I_9_1a | L822: N91a | M822: 365 | N822: AUXILIAR DE ENFERMERÍA | O822: PLANTILLA VOLANTE | P822: DIRECCIÓN DE ENFERMERÍA | Q822: 0 | U822: 46387
A823: 390544 | B823: 78570401D | C823: LESTON RAMOS, JASMINA DEBORA | D823: 46023 | E823: 46387 | F823: 175506 | G823: TEMPORAL. T. COM. INTER. N. ESTA | H823: INTERINO POR VACANTE | I823: AUXILIAR DE ENFERMERÍA | J823: E | K823: I_9_1a | L823: N91a | M823: 365 | N823: AUXILIAR DE ENFERMERÍA | O823: PLANTILLA VOLANTE | P823: DIRECCIÓN DE ENFERMERÍA | Q823: 0 | U823: 46387 | V823: 46387 | W823: =_xlfn.DAYS(V823,U823) -> 0
A824: 231172 | B824: 43839287E | C824: LOPEZ MORENO, EDGAR | D824: 46023 | E824: 46387 | F824: 170787 | G824: TEMPORAL. T. COM. INTER. N. ESTA | H824: INTERINO POR VACANTE | I824: ENFERMERO/A | J824: E | K824: I_9_1a | L824: N91a | M824: 365 | N824: ENFERMERA/O | O824: PLANTILLA VOLANTE | P824: DIRECCIÓN DE ENFERMERÍA | Q824: 0 | U824: 46387 | V824: 46387 | W824: =_xlfn.DAYS(V824,U824) -> 0
A825: 375466 | B825: 43781282T | C825: MARTIN ALVAREZ, JOSE MANUEL | D825: 46023 | E825: 46387 | F825: 169960 | G825: TEMPORAL. T. COM. INTER. N. ESTA | H825: INTERINO POR VACANTE | I825: AUXILIAR DE ENFERMERÍA | J825: E | K825: I_9_1a | L825: N91a | M825: 365 | N825: AUXILIAR DE ENFERMERÍA | O825: PLANTILLA VOLANTE | P825: DIRECCIÓN DE ENFERMERÍA | Q825: 0 | U825: 46387 | V825: 46387 | W825: =_xlfn.DAYS(V825,U825) -> 0
A826: 245540 | B826: 48831594H | C826: MARTINEZ PALAO, FERNANDO | D826: 46023 | E826: 46387 | F826: 170779 | G826: TEMPORAL. T. COM. INTER. N. ESTA | H826: INTERINO POR VACANTE | I826: ENFERMERO/A | J826: E | K826: I_9_1a | L826: N91a | M826: 365 | N826: ENFERMERA/O | O826: PLANTILLA VOLANTE | P826: DIRECCIÓN DE ENFERMERÍA | Q826: 0 | U826: 46387 | V826: 46387 | W826: =_xlfn.DAYS(V826,U826) -> 0
A827: 295002 | B827: 45604885W | C827: MARTINEZ PARRA, JAIME | D827: 46023 | E827: 46387 | F827: 169748 | G827: TEMPORAL. T. COM. INTER. N. ESTA | H827: INTERINO POR VACANTE | I827: ENFERMERO/A | J827: E | K827: I_9_1a | L827: N91a | M827: 365 | N827: ENFERMERA/O | O827: PLANTILLA VOLANTE | P827: DIRECCIÓN DE ENFERMERÍA | Q827: 0 | U827: 46387 | V827: 46387 | W827: =_xlfn.DAYS(V827,U827) -> 0
A828: 377653 | B828: 49148476Y | C828: MORANO CORRALES, MARIA | D828: 46023 | E828: 46387 | F828: 170773 | G828: TEMPORAL. T. COM. INTER. N. ESTA | H828: INTERINO POR VACANTE | I828: ENFERMERO/A | J828: E | K828: I_9_1a | L828: N91a | M828: 365 | N828: ENFERMERA/O | O828: PLANTILLA VOLANTE | P828: DIRECCIÓN DE ENFERMERÍA | Q828: 0 | U828: 46387 | V828: 46387 | W828: =_xlfn.DAYS(V828,U828) -> 0
A829: 217022 | B829: 77020401W | C829: MORENO RUIZ, MINERVA | D829: 46023 | E829: 46387 | F829: 174405 | G829: TEMPORAL. T. COM. INTER. N. ESTA | H829: INTERINO POR VACANTE | I829: ENFERMERO/A | J829: E | K829: I_9_1a | L829: N91a | M829: 365 | N829: ENFERMERA/O | O829: PLANTILLA VOLANTE | P829: DIRECCIÓN DE ENFERMERÍA | Q829: 0 | U829: 46387 | V829: 46387 | W829: =_xlfn.DAYS(V829,U829) -> 0
A830: 213804 | B830: 54052098M | C830: NEGRIN RODRIGUEZ, ANDREA MARIA | D830: 46023 | E830: 46387 | F830: 162368 | G830: TEMPORAL. T. COM. INTER. N. ESTA | H830: INTERINO POR VACANTE | I830: ENFERMERO/A | J830: E | K830: I_9_1a | L830: N91a | M830: 365 | N830: ENFERMERA/O | O830: PLANTILLA VOLANTE | P830: DIRECCIÓN DE ENFERMERÍA | Q830: 0 | U830: 46387 | V830: 46387 | W830: =_xlfn.DAYS(V830,U830) -> 0
A831: 263906 | B831: 78680168C | C831: NUÑEZ SUAREZ, JUANA MARIA | D831: 46023 | E831: 46387 | F831: 161147 | G831: TEMPORAL. T. COM. INTER. N. ESTA | H831: INTERINO POR VACANTE | I831: AUXILIAR DE ENFERMERÍA | J831: E | K831: I_9_1a | L831: N91a | M831: 365 | N831: AUXILIAR DE ENFERMERÍA | O831: PLANTILLA VOLANTE | P831: DIRECCIÓN DE ENFERMERÍA | Q831: 0 | U831: 46387 | V831: 46387 | W831: =_xlfn.DAYS(V831,U831) -> 0
A832: 227504 | B832: 54108629W | C832: PADILLA HERNANDEZ, YAIZA | D832: 46023 | E832: 46387 | F832: 174286 | G832: TEMPORAL. T. COM. INTER. N. ESTA | H832: INTERINO POR VACANTE | I832: AUXILIAR DE ENFERMERÍA | J832: E | K832: I_9_1a | L832: N91a | M832: 365 | N832: AUXILIAR DE ENFERMERÍA | O832: PLANTILLA VOLANTE | P832: DIRECCIÓN DE ENFERMERÍA | Q832: 0 | U832: 46387 | V832: 46387 | W832: =_xlfn.DAYS(V832,U832) -> 0
A833: 200191 | B833: 43486246P | C833: PALENZUELA ALVAREZ, THALIA | D833: 46023 | E833: 46387 | F833: 174421 | G833: TEMPORAL. T. COM. INTER. N. ESTA | H833: INTERINO POR VACANTE | I833: ENFERMERO/A | J833: E | K833: I_9_1a | L833: N91a | M833: 365 | N833: ENFERMERA/O | O833: PLANTILLA VOLANTE | P833: DIRECCIÓN DE ENFERMERÍA | Q833: 0 | U833: 46387 | V833: 46387 | W833: =_xlfn.DAYS(V833,U833) -> 0
A834: 226972 | B834: 78624619Q | C834: PERDOMO PEREZ, MARIA YURENA | D834: 46023 | E834: 46387 | F834: 169913 | G834: TEMPORAL. T. COM. INTER. N. ESTA | H834: INTERINO POR VACANTE | I834: AUXILIAR DE ENFERMERÍA | J834: E | K834: I_9_1a | L834: N91a | M834: 365 | N834: AUXILIAR DE ENFERMERÍA | O834: PLANTILLA VOLANTE | P834: DIRECCIÓN DE ENFERMERÍA | Q834: 0 | U834: 46387 | V834: 46387 | W834: =_xlfn.DAYS(V834,U834) -> 0
... A878: 329736 | B878: 45448045E | C878: DOPAZO LUQUE, DAVID | D878: 46113 | E878: 46387 | F878: 178022 | G878: TEMPORAL. T. COM. INTER. N. ESTA | H878: INTERINO POR VACANTE | I878: ENFERMERO/A | J878: E | K878: I_9_1a | L878: N91a | M878: 275 | N878: ENFERMERA/O | O878: RADIOLOG.VASCULAR INTERV. - ANGIORADIOL. | P878: DIRECCIÓN DE ENFERMERÍA | Q878: 0 | U878: 46387 | V878: 46387 | W878: =_xlfn.DAYS(V878,U878) -> 0
A879: 238646 | B879: 42224250E | C879: ARIZMENDI SANCHEZ, LAURA | D879: 46023 | E879: 46387 | F879: 154043 | G879: TEMPORAL. T. COM. INTER. N. ESTA | H879: INTERINO POR VACANTE | I879: TÉC ESPECIALISTA / RADIODIAGNÓSTICO | J879: E | K879: I_9_1a | L879: N91a | M879: 365 | N879: TÉCNICO ESPECIALISTA RADIODIAGNÓSTICO | O879: RADIOLOGÍA DE URGENCIAS | P879: DIRECCIÓN DE ENFERMERÍA | Q879: 0 | U879: 46387
A880: 233871 | B880: 53782081P | C880: BRAVO FERNANDEZ, ADRIAN | D880: 46023 | E880: 46387 | F880: 154495 | G880: TEMPORAL. T. COM. INTER. N. ESTA | H880: INTERINO POR VACANTE | I880: TÉC ESPECIALISTA / RADIODIAGNÓSTICO | J880: E | K880: I_9_1a | L880: N91a | M880: 365 | N880: TÉCNICO ESPECIALISTA RADIODIAGNÓSTICO | O880: RADIOLOGÍA DE URGENCIAS | P880: DIRECCIÓN DE ENFERMERÍA | Q880: 0 | U880: 46387
A881: 294443 | B881: 48122821J | C881: GALLEGOS RODRIGUEZ, GUILLERMO | D881: 46023 | E881: 46387 | F881: 170597 | G881: TEMPORAL. T. COM. INTER. N. ESTA | H881: INTERINO POR VACANTE | I881: ENFERMERO/A | J881: E | K881: I_9_1a | L881: N91a | M881: 365 | N881: ENFERMERA/O | O881: RADIOLOGÍA DE URGENCIAS | P881: DIRECCIÓN DE ENFERMERÍA | Q881: 0 | U881: 46387
A882: 209169 | B882: 32887072Q | C882: GONZALEZ CARBALLO, PATRICIA | D882: 46023 | E882: 46387 | F882: 154037 | G882: TEMPORAL. T. COM. INTER. N. ESTA | H882: INTERINO POR VACANTE | I882: TÉC ESPECIALISTA / RADIODIAGNÓSTICO | J882: E | K882: I_9_1a | L882: N91a | M882: 365 | N882: TÉCNICO ESPECIALISTA RADIODIAGNÓSTICO | O882: RADIOLOGÍA DE URGENCIAS | P882: DIRECCIÓN DE ENFERMERÍA | Q882: 0 | U882: 46387
A883: 257948 | B883: 21684824X | C883: LLACER MARTINEZ, YURENA | D883: 46023 | E883: 46387 | F883: 154035 | G883: TEMPORAL. T. COM. INTER. N. ESTA | H883: INTERINO POR VACANTE | I883: TÉC ESPECIALISTA / RADIODIAGNÓSTICO | J883: E | K883: I_9_1a | L883: N91a | M883: 365 | N883: TÉCNICO ESPECIALISTA RADIODIAGNÓSTICO | O883: RADIOLOGÍA DE URGENCIAS | P883: DIRECCIÓN DE ENFERMERÍA | Q883: 0 | U883: 46387
A884: 231651 | B884: 54057972Z | C884: MOLINA HERRERA, YVONNE | D884: 46023 | E884: 46387 | F884: 154039 | G884: TEMPORAL. T. COM. INTER. N. ESTA | H884: INTERINO POR VACANTE | I884: TÉC ESPECIALISTA / RADIODIAGNÓSTICO | J884: E | K884: I_9_1a | L884: N91a | M884: 365 | N884: TÉCNICO ESPECIALISTA RADIODIAGNÓSTICO | O884: RADIOLOGÍA DE URGENCIAS | P884: DIRECCIÓN DE ENFERMERÍA | Q884: 0 | U884: 46387
A885: 247087 | B885: 38146877C | C885: NAVARRO OLIVA, OSCAR | D885: 46023 | E885: 46387 | F885: 154045 | G885: TEMPORAL. T. COM. INTER. N. ESTA | H885: INTERINO POR VACANTE | I885: TÉC ESPECIALISTA / RADIODIAGNÓSTICO | J885: E | K885: I_9_1a | L885: N91a | M885: 365 | N885: TÉCNICO ESPECIALISTA RADIODIAGNÓSTICO | O885: RADIOLOGÍA DE URGENCIAS | P885: DIRECCIÓN DE ENFERMERÍA | Q885: 0 | U885: 46387
A886: 342563 | B886: 54047172R | C886: PAIZ CABRERA, JAIME | D886: 46023 | E886: 46387 | F886: 169806 | G886: TEMPORAL. T. COM. INTER. N. ESTA | H886: INTERINO POR VACANTE | I886: TÉC ESPECIALISTA / RADIODIAGNÓSTICO | J886: E | K886: I_9_1a | L886: N91a | M886: 365 | N886: TÉCNICO ESPECIALISTA RADIODIAGNÓSTICO | O886: RADIOLOGÍA DE URGENCIAS | P886: DIRECCIÓN DE ENFERMERÍA | Q886: 0 | U886: 46387
A887: 266151 | B887: 79064050D | C887: PITTI PEREZ, JORGE | D887: 46023 | E887: 46387 | F887: 169808 | G887: TEMPORAL. T. COM. INTER. N. ESTA | H887: INTERINO POR VACANTE | I887: TÉC ESPECIALISTA / RADIODIAGNÓSTICO | J887: E | K887: I_9_1a | L887: N91a | M887: 365 | N887: TÉCNICO ESPECIALISTA RADIODIAGNÓSTICO | O887: RADIOLOGÍA DE URGENCIAS | P887: DIRECCIÓN DE ENFERMERÍA | Q887: 0 | U887: 46387
A888: 204929 | B888: 79086777N | C888: RODRIGUEZ GONZALEZ, LETICIA | D888: 46023 | E888: 46387 | F888: 154668 | G888: TEMPORAL. T. COM. INTER. N. ESTA | H888: INTERINO POR VACANTE | I888: ENFERMERO/A | J888: E | K888: I_9_1a | L888: N91a | M888: 365 | N888: ENFERMERA/O | O888: RADIOLOGÍA DE URGENCIAS | P888: DIRECCIÓN DE ENFERMERÍA | Q888: 0 | U888: 46387
A889: 294317 | B889: 79075531J | C889: RODRIGUEZ RODRIGUEZ, HIMILCE RAQUEL | D889: 46023 | E889: 46387 | F889: 169814 | G889: TEMPORAL. T. COM. INTER. N. ESTA | H889: INTERINO POR VACANTE | I889: TÉC ESPECIALISTA / RADIODIAGNÓSTICO | J889: E | K889: I_9_1a | L889: N91a | M889: 365 | N889: TÉCNICO ESPECIALISTA RADIODIAGNÓSTICO | O889: RADIOLOGÍA DE URGENCIAS | P889: DIRECCIÓN DE ENFERMERÍA | Q889: 0 | U889: 46387
A890: 217690 | B890: 78619938G | C890: SANCHEZ GUTIERREZ, ANA INMACULADA | D890: 46023 | E890: 46387 | F890: 154036 | G890: TEMPORAL. T. COM. INTER. N. ESTA | H890: INTERINO POR VACANTE | I890: TÉC ESPECIALISTA / RADIODIAGNÓSTICO | J890: E | K890: I_9_1a | L890: N91a | M890: 365 | N890: TÉCNICO ESPECIALISTA RADIODIAGNÓSTICO | O890: RADIOLOGÍA DE URGENCIAS | P890: DIRECCIÓN DE ENFERMERÍA | Q890: 0 | U890: 46387
... A1890: 212638 | B1890: 05942751B | C1890: RODRIGUEZ VILLEGAS, BEATRIZ | D1890: 46023 | E1890: 46134 | F1890: 165653 | G1890: TEMPORAL. T. COMPLETO. N. ESTATU | H1890: PROGRAMA CARACTER TEMPORAL | I1890: FEA OBSTETRICIA Y GINECOLOGÍA | J1890: E | K1890: I_9_1b | L1890: N91b | M1890: 112 | N1890: FEA OBSTETRICIA Y GINECOLOGÍA | O1890: P.MÉDICO GINECOLOGÍA | P1890: DIRECCIÓN MÉDICA | Q1890: 0 | U1890: 46134
A1891: 269987 | B1891: 45110952V | C1891: ROSADO MUÑOZ, CRISTINA | D1891: 46023 | E1891: 46153 | F1891: 172646 | G1891: TEMPORAL. T. COMPLETO. N. ESTATU | H1891: PROGRAMA CARACTER TEMPORAL | I1891: FEA MEDICINA INTENSIVA | J1891: E | K1891: I_9_1b | L1891: N91b | M1891: 131 | N1891: FEA MEDICINA INTENSIVA | O1891: P.MÉDICO U.V.I: | P1891: DIRECCIÓN MÉDICA | Q1891: 0 | U1891: 46153 | V1891: 46387 | W1891: =_xlfn.DAYS(V1891,U1891) -> 234
A1892: 273179 | B1892: 78621161P | C1892: LUIS GONZALEZ, MONICA | D1892: 46065 | E1892: 46153 | F1892: 176660 | G1892: TEMPORAL. T. COMPLETO. N. ESTATU | H1892: PROGRAMA CARACTER TEMPORAL | I1892: TRABAJADOR/A SOCIAL | J1892: E | K1892: I_9_1b | L1892: N91b | M1892: 89 | N1892: TRABAJADOR /A SOCIAL | O1892: TRABAJO SOCIAL | P1892: GERENCIA | Q1892: 0 | U1892: 46153 | V1892: 46387 | W1892: =_xlfn.DAYS(V1892,U1892) -> 234
A1893: 296348 | B1893: 30237262J | C1893: CALLEJON FERNANDEZ, MANUEL | D1893: 46023 | E1893: 46173 | F1893: 152923 | G1893: TEMPORAL. T. COMPLETO. N. ESTATU | H1893: PROGRAMA CARACTER TEMPORAL | I1893: FEA MICROBIOLOGÍA Y PARASITOLOGÍA | J1893: E | K1893: I_9_1b | L1893: N91b | M1893: 151 | N1893: FEA MICROBIOLOGÍA Y PARASITOLOGÍA | O1893: P.MÉDICO MICROBIOLOGÍA Y CONTROL INFECCI | P1893: DIRECCIÓN MÉDICA | Q1893: 0 | U1893: 46173 | V1893: 46387 | W1893: =_xlfn.DAYS(V1893,U1893) -> 214
A1894: 256973 | B1894: 51150494N | C1894: TERAN GARCIA, ELENA | D1894: 46023 | E1894: 46173 | F1894: 152913 | G1894: TEMPORAL. T. COMPLETO. N. ESTATU | H1894: PROGRAMA CARACTER TEMPORAL | I1894: FEA NEFROLOGÍA | J1894: E | K1894: I_9_1b | L1894: N91b | M1894: 151 | N1894: FEA NEFROLOGÍA | O1894: P.MÉDICO NEFROLOGÍA | P1894: DIRECCIÓN MÉDICA | Q1894: 0 | U1894: 46173 | V1894: 46387 | W1894: =_xlfn.DAYS(V1894,U1894) -> 214
A1895: 304980 | B1895: 78854179J | C1895: FOX CONCEPCION, PATRICIA PILAR | D1895: 46023 | E1895: 46202 | F1895: 170849 | G1895: TEMPORAL. T. COMPLETO. N. ESTATU | H1895: PROGRAMA CARACTER TEMPORAL | I1895: FEA NEFROLOGÍA | J1895: E | K1895: I_9_1b | L1895: N91b | M1895: 180 | N1895: FEA NEFROLOGÍA | O1895: P.MÉDICO NEFROLOGÍA | P1895: DIRECCIÓN MÉDICA | Q1895: 0 | U1895: 46202 | V1895: 46387 | W1895: =_xlfn.DAYS(V1895,U1895) -> 185
A1896: 214272 | B1896: 71675888E | C1896: FERNANDEZ SOLIS, JUAN | D1896: 46023 | E1896: 46223 | F1896: 171205 | G1896: TEMPORAL. T. COMPLETO. N. ESTATU | H1896: PROGRAMA CARACTER TEMPORAL | I1896: FEA NEFROLOGÍA | J1896: E | K1896: I_9_1b | L1896: N91b | M1896: 201 | N1896: FEA NEFROLOGÍA | O1896: P.MÉDICO NEFROLOGÍA | P1896: DIRECCIÓN MÉDICA | Q1896: 0 | U1896: 46223 | V1896: 46387 | W1896: =_xlfn.DAYS(V1896,U1896) -> 164
A1897: 226541 | B1897: 43834548K | C1897: CHICO GONZALEZ, TANIA MARLEM | D1897: 46023 | E1897: 46253 | F1897: 171780 | G1897: TEMPORAL. T. COMPLETO. N. ESTATU | H1897: PROGRAMA CARACTER TEMPORAL | I1897: FEA RADIODIAGNÓSTICO | J1897: E | K1897: I_9_1b | L1897: N91b | M1897: 231 | N1897: FEA RADIODIAGNÓSTICO | O1897: P.MÉDICO RADIODIAGNÓSTICO | P1897: DIRECCIÓN MÉDICA | Q1897: 0 | U1897: 46253 | V1897: 46387 | W1897: =_xlfn.DAYS(V1897,U1897) -> 134
A1898: 272410 | B1898: 54113874A | C1898: MESA DELGADO, PATRICIA | D1898: 46054 | E1898: 46387 | F1898: 176331 | G1898: TEMPORAL. T. COMPLETO. N. ESTATU | H1898: PROGRAMA CARACTER TEMPORAL | I1898: ENFERMERO ESPECIALISTA SALUD MENTAL | J1898: E | K1898: I_9_1b | L1898: N91b | M1898: 334 | N1898: ENFERMERA/O ESPECIALISTA EN ENFERMERÍA DE SALUD ME | O1898: PLANTA 2ª CENTRAL B - EDIF.B | P1898: DIRECCIÓN DE ENFERMERÍA | Q1898: 0 | U1898: 46387
A1899: 368292 | B1899: 78628911F | C1899: ACOSTA RODRIGUEZ, ELENA | D1899: 46054 | E1899: 46387 | F1899: 176330 | G1899: TEMPORAL. T. COMPLETO. N. ESTATU | H1899: PROGRAMA CARACTER TEMPORAL | I1899: ENFERMERO ESPECIALISTA SALUD MENTAL | J1899: E | K1899: I_9_1b | L1899: N91b | M1899: 334 | N1899: ENFERMERA/O ESPECIALISTA EN ENFERMERÍA DE SALUD ME | O1899: UNIDAD DE SALUD MENTAL INFANTO JUVENIL | P1899: DIRECCIÓN DE ENFERMERÍA | Q1899: 0 | U1899: 46387
A1900: 298600 | B1900: 79075375H | C1900: ACOSTA SORIA, VERONICA | D1900: 46023 | E1900: 46387 | F1900: 171655 | G1900: TEMPORAL. T. COMPLETO. N. ESTATU | H1900: PROGRAMA CARACTER TEMPORAL | I1900: FEA MEDICINA DEL TRABAJO | J1900: E | K1900: I_9_1b | L1900: N91b | M1900: 365 | N1900: FEA MEDICINA DEL TRABAJO | O1900: SERVICIO DE PREVENCION Y MED.DEL TRABAJO | P1900: DIRECCIÓN DE RR.HH. | Q1900: 0 | U1900: 46387
A1901: 253152 | B1901: 60629156Y | C1901: ROLINGSON LANDAETA, JAIME LEONARDO | D1901: 46023 | E1901: 46387 | F1901: 171522 | G1901: TEMPORAL. T. COMPLETO. N. ESTATU | H1901: PROGRAMA CARACTER TEMPORAL | I1901: FEA FARMACOLOGÍA CLÍNICA | J1901: E | K1901: I_9_1b | L1901: N91b | M1901: 365 | N1901: FEA FARMACOLOGÍA CLÍNICA | O1901: FARMACOLOGÍA CLÍNICA | P1901: DIRECCIÓN MÉDICA | Q1901: 0 | U1901: 46387
A1902: 250933 | B1902: 43380940L | C1902: DIAZ CALZADILLA, PABLO | D1902: 46023 | E1902: 46387 | F1902: 171602 | G1902: TEMPORAL. T. COMPLETO. N. ESTATU | H1902: PROGRAMA CARACTER TEMPORAL | I1902: FEA RADIOFÍSICA HOSPITALARIA | J1902: E | K1902: I_9_1b | L1902: N91b | M1902: 365 | N1902: FEA RADIOFÍSICA HOSPITALARIA | O1902: FÍSICA MÉDICA (UDAD.TÉC.RADIOPROTECCIÓN) | P1902: DIRECCIÓN MÉDICA | Q1902: 0 | U1902: 46387
A1903: 220283 | B1903: 79063018N | C1903: LOPEZ HENRIQUEZ, ROCIO | D1903: 46023 | E1903: 46387 | F1903: 171284 | G1903: TEMPORAL. T. COMPLETO. N. ESTATU | H1903: PROGRAMA CARACTER TEMPORAL | I1903: FEA ANATOMÍA PATOLÓGICA | J1903: E | K1903: I_9_1b | L1903: N91b | M1903: 365 | N1903: FEA ANATOMÍA PATOLÓGICA | O1903: P.MÉDICO ANATOMÍA PATOLÓGICA | P1903: DIRECCIÓN MÉDICA | Q1903: 0 | U1903: 46387
A1904: 347073 | B1904: 78528523Z | C1904: DIAZ SANCHEZ, OCTAVIO RUBEN | D1904: 46023 | E1904: 46387 | F1904: 171285 | G1904: TEMPORAL. T. COMPLETO. N. ESTATU | H1904: PROGRAMA CARACTER TEMPORAL | I1904: FEA ANESTESIOLOGÍA Y REANIMACIÓN | J1904: E | K1904: I_9_1b | L1904: N91b | M1904: 365 | N1904: FEA ANESTESIOLOGÍA Y REANIMACIÓN | O1904: P.MÉDICO ANESTESIA | P1904: DIRECCIÓN MÉDICA | Q1904: 0 | U1904: 46387
A1905: 230520 | B1905: 78642608L | C1905: HERNANDEZ MESA, ADRIAN | D1905: 46023 | E1905: 46387 | F1905: 171288 | G1905: TEMPORAL. T. COMPLETO. N. ESTATU | H1905: PROGRAMA CARACTER TEMPORAL | I1905: FEA ANESTESIOLOGÍA Y REANIMACIÓN | J1905: E | K1905: I_9_1b | L1905: N91b | M1905: 365 | N1905: FEA ANESTESIOLOGÍA Y REANIMACIÓN | O1905: P.MÉDICO ANESTESIA | P1905: DIRECCIÓN MÉDICA | Q1905: 0 | U1905: 46387
A1906: 205293 | B1906: 79075380T | C1906: SAN LUIS ARRANZ, BEGOÑA | D1906: 46023 | E1906: 46387 | F1906: 171287 | G1906: TEMPORAL. T. COMPLETO. N. ESTATU | H1906: PROGRAMA CARACTER TEMPORAL | I1906: FEA ANESTESIOLOGÍA Y REANIMACIÓN | J1906: E | K1906: I_9_1b | L1906: N91b | M1906: 365 | N1906: FEA ANESTESIOLOGÍA Y REANIMACIÓN | O1906: P.MÉDICO ANESTESIA | P1906: DIRECCIÓN MÉDICA | Q1906: 0 | U1906: 46387
A1907: 295818 | B1907: 78640647J | C1907: TRUJILLO BURILLO, DAVID | D1907: 46023 | E1907: 46387 | F1907: 171286 | G1907: TEMPORAL. T. COMPLETO. N. ESTATU | H1907: PROGRAMA CARACTER TEMPORAL | I1907: FEA ANESTESIOLOGÍA Y REANIMACIÓN | J1907: E | K1907: I_9_1b | L1907: N91b | M1907: 365 | N1907: FEA ANESTESIOLOGÍA Y REANIMACIÓN | O1907: P.MÉDICO ANESTESIA | P1907: DIRECCIÓN MÉDICA | Q1907: 0 | U1907: 46387
A1908: 248740 | B1908: 54064057G | C1908: CASTRO MARTIN, JORGE JOAQUIN | D1908: 46023 | E1908: 46387 | F1908: 172536 | G1908: TEMPORAL. T. COMPLETO. N. ESTATU | H1908: PROGRAMA CARACTER TEMPORAL | I1908: FEA CARDIOLOGÍA | J1908: E | K1908: I_9_1b | L1908: N91b | M1908: 365 | N1908: FEA CARDIOLOGÍA | O1908: P.MÉDICO CARDIOLOGÍA | P1908: DIRECCIÓN MÉDICA | Q1908: 0 | U1908: 46387
A1909: 270973 | B1909: 78646310H | C1909: RIVERO GARCIA, MANUEL ALEJANDRO | D1909: 46023 | E1909: 46387 | F1909: 172537 | G1909: TEMPORAL. T. COMPLETO. N. ESTATU | H1909: PROGRAMA CARACTER TEMPORAL | I1909: FEA CARDIOLOGÍA | J1909: E | K1909: I_9_1b | L1909: N91b | M1909: 365 | N1909: FEA CARDIOLOGÍA | O1909: P.MÉDICO CARDIOLOGÍA | P1909: DIRECCIÓN MÉDICA | Q1909: 0 | U1909: 46387
... A2053: 348961 | B2053: 78710888N | C2053: MARTIN DIONIS, ANA CATAISA | D2053: 46023 | E2053: 46072 | F2053: 169500 | G2053: SIN CONTRATO | H2053: OTRA DIRECCIÓN GERENCIA-PROMOCION INTERNA TEMPORAL | I2053: G GESTIÓN FUNCIÓN ADMINISTRATIVA | J2053: E | K2053: I_9_1c | L2053: N91c | M2053: 50 | N2053: GRUPO GESTIÓN FUNCIÓN ADMINISTRATIVA | O2053: CONTRATACIÓN ADMINISTRATIVA | P2053: Dirección Planificación y Gestión RREE | Q2053: 0 | U2053: 46072
A2054: 212913 | B2054: 43782816Q | C2054: MELIAN GARCIA, ANA LEIDA | D2054: 46054 | E2054: 46073 | F2054: 176275 | G2054: TEMPORAL. T. PARCIAL. N. ESTATU. | H2054: ACUMULACION DE TAREAS | I2054: TÉCNICA/O AUXILIAR DE FARMACIA | J2054: E | K2054: I_9_1c | L2054: N91c | M2054: 20 | N2054: TÉCNICA/O AUXILIAR DE FARMACIA | O2054: ALMACÉN DE FARMACIA | P2054: DIRECCIÓN DE ENFERMERÍA | Q2054: 200733 | R2054: 78857015C | S2054: FLORES CONTRERAS, ANA BEATRIZ | T2054: GRUPO ADMINISTRATIVO | U2054: 46073
A2055: 309631 | B2055: 73104548Z | C2055: ZAPATER LOPEZ, RAUL | D2055: 46023 | E2055: 46075 | F2055: 170421 | G2055: TEMPORAL. T. COMPLETO. N. ESTATU | H2055: ACUMULACION DE TAREAS | I2055: FEA APARATO DIGESTIVO | J2055: E | K2055: I_9_1c | L2055: N91c | M2055: 53 | N2055: FEA APARATO DIGESTIVO | O2055: P.MÉDICO DIGESTIVO | P2055: DIRECCIÓN MÉDICA | Q2055: 0 | U2055: 46075
A2056: 244114 | B2056: Y8753133Z | C2056: QUEZADA PERALTA, GONZALO ELIAS | D2056: 46023 | E2056: 46075 | F2056: 171772 | G2056: TEMPORAL. T. COMPLETO. N. ESTATU | H2056: ACUMULACION DE TAREAS | I2056: FEA OFTALMOLOGÍA | J2056: E | K2056: I_9_1c | L2056: N91c | M2056: 53 | N2056: FEA OFTALMOLOGÍA | O2056: P.MÉDICO OFTALMOLOGÍA | P2056: DIRECCIÓN MÉDICA | Q2056: 0 | U2056: 46075
A2057: 223359 | B2057: 42222994P | C2057: ALVAREZ DE LA CRUZ, JAVIER | D2057: 46023 | E2057: 46075 | F2057: 170719 | G2057: TEMPORAL. T. COMPLETO. N. ESTATU | H2057: ACUMULACION DE TAREAS | I2057: FEA CIRUGÍA ORTOPÉDICA Y TRAUMATOLOGÍA | J2057: E | K2057: I_9_1c | L2057: N91c | M2057: 53 | N2057: FEA CIRUGÍA ORTOPÉDICA Y TRAUMATOLOGÍA | O2057: P.MÉDICO TRAUMA | P2057: DIRECCIÓN MÉDICA | Q2057: 0 | U2057: 46075
A2058: 284609 | B2058: 04726518H | C2058: GARCIA EXPOSITO, LAHIS DEL CARMEN | D2058: 46023 | E2058: 46079 | F2058: 172948 | G2058: TEMPORAL. T. COMPLETO. N. ESTATU | H2058: ACUMULACION DE TAREAS | I2058: MEDICO/A URGENCIA HOSPITALARIA | J2058: E | K2058: I_9_1c | L2058: N91c | M2058: 57 | N2058: MÉDICO URGENCIA HOSPITALARIA | O2058: P.MÉDICO DE URGENCIAS | P2058: DIRECCIÓN MÉDICA | Q2058: 0 | U2058: 46079
A2059: 250863 | B2059: 45454134Q | C2059: BOLAÑOS AVILA, MARIA DEL CARMEN | D2059: 46054 | E2059: 46081 | F2059: 176125 | G2059: TEMPORAL. T. COMPLETO. N. ESTATU | H2059: ACUMULACION DE TAREAS | I2059: AUXILIAR DE ENFERMERÍA | J2059: E | K2059: I_9_1c | L2059: N91c | M2059: 28 | N2059: AUXILIAR DE ENFERMERÍA | O2059: AREA.ENFERMERIA - CAE LA LAGUNA-GENETO | P2059: DIRECCIÓN DE ENFERMERÍA | Q2059: 0 | U2059: 46081
A2060: 381287 | B2060: 78559474F | C2060: HERNANDEZ SUAREZ, MARIA ELENA | D2060: 46054 | E2060: 46081 | F2060: 175712 | G2060: TEMPORAL. T. PARCIAL. N. ESTATU. | H2060: ACUMULACION DE TAREAS | I2060: TÉC ESPECIALISTA / RADIODIAGNÓSTICO | J2060: E | K2060: I_9_1c | L2060: N91c | M2060: 28 | N2060: TÉCNICO ESPECIALISTA RADIODIAGNÓSTICO | O2060: AREA.ENFERMERIA - CAE PTO.DE LA CRUZ | P2060: DIRECCIÓN DE ENFERMERÍA | Q2060: 0 | U2060: 46081
A2061: 241139 | B2061: 78635810Y | C2061: RODRIGUEZ DORTA, LAURA | D2061: 46054 | E2061: 46081 | F2061: 175711 | G2061: TEMPORAL. T. PARCIAL. N. ESTATU. | H2061: ACUMULACION DE TAREAS | I2061: TÉC ESPECIALISTA / RADIODIAGNÓSTICO | J2061: E | K2061: I_9_1c | L2061: N91c | M2061: 28 | N2061: TÉCNICO ESPECIALISTA RADIODIAGNÓSTICO | O2061: AREA.ENFERMERIA - CAE PTO.DE LA CRUZ | P2061: DIRECCIÓN DE ENFERMERÍA | Q2061: 0 | U2061: 46081
A2062: 384325 | B2062: 70654912Q | C2062: FRANCEZON MONJE, STELLA MARIS | D2062: 46054 | E2062: 46081 | F2062: 175710 | G2062: TEMPORAL. T. COMPLETO. N. ESTATU | H2062: ACUMULACION DE TAREAS | I2062: TÉC ESPECIALISTA / RADIODIAGNÓSTICO | J2062: E | K2062: I_9_1c | L2062: N91c | M2062: 28 | N2062: TÉCNICO ESPECIALISTA RADIODIAGNÓSTICO | O2062: BLOQUE QUIRURGICO CENTRAL | P2062: DIRECCIÓN DE ENFERMERÍA | Q2062: 0 | U2062: 46081
A2063: 373139 | B2063: 54054199J | C2063: LOPEZ GONZALEZ, NAYRA | D2063: 46069 | E2063: 46081 | F2063: 176719 | G2063: TEMPORAL. T. COMPLETO. N. ESTATU | H2063: ACUMULACION DE TAREAS | I2063: ENFERMERO/A | J2063: E | K2063: I_9_1c | L2063: N91c | M2063: 13 | N2063: ENFERMERA/O | O2063: PLANTA 2ª - HOSPITAL DEL NORTE | P2063: DIRECCIÓN DE ENFERMERÍA | Q2063: 0 | U2063: 46081
A2064: 336172 | B2064: 43837480D | C2064: RODRIGUEZ GONZALEZ, SARA | D2064: 46071 | E2064: 46081 | F2064: 176722 | G2064: TEMPORAL. T. COMPLETO. N. ESTATU | H2064: ACUMULACION DE TAREAS | I2064: ENFERMERO/A | J2064: E | K2064: I_9_1c | L2064: N91c | M2064: 11 | N2064: ENFERMERA/O | O2064: PLANTA 2ª - HOSPITAL DEL NORTE | P2064: DIRECCIÓN DE ENFERMERÍA | Q2064: 0 | U2064: 46081
A2065: 380210 | B2065: 43773380X | C2065: ACOSTA FERNANDEZ, BEATRIZ YOLANDA | D2065: 46054 | E2065: 46081 | F2065: 176127 | G2065: TEMPORAL. T. COMPLETO. N. ESTATU | H2065: ACUMULACION DE TAREAS | I2065: AUXILIAR DE ENFERMERÍA | J2065: E | K2065: I_9_1c | L2065: N91c | M2065: 28 | N2065: AUXILIAR DE ENFERMERÍA | O2065: PLANTILLA VOLANTE | P2065: DIRECCIÓN DE ENFERMERÍA | Q2065: 0 | U2065: 46081
A2066: 262805 | B2066: 42240771Y | C2066: ACOSTA MARTIN, CAROLINA | D2066: 46054 | E2066: 46081 | F2066: 176119 | G2066: TEMPORAL. T. COMPLETO. N. ESTATU | H2066: ACUMULACION DE TAREAS | I2066: AUXILIAR DE ENFERMERÍA | J2066: E | K2066: I_9_1c | L2066: N91c | M2066: 28 | N2066: AUXILIAR DE ENFERMERÍA | O2066: PLANTILLA VOLANTE | P2066: DIRECCIÓN DE ENFERMERÍA | Q2066: 0 | U2066: 46081
... A2482: 251741 | B2482: 42240062X | C2482: REY SANTANA, JESICA MARIA | D2482: 46150 | E2482: 46156 | F2482: 179196 | G2482: TEMPORAL. T. COMPLETO. N. ESTATU | H2482: ACUMULACION DE TAREAS | I2482: AUXILIAR DE ENFERMERÍA | J2482: E | K2482: I_9_1c | L2482: N91c | M2482: 7 | N2482: AUXILIAR DE ENFERMERÍA | O2482: PLANTA BAJA - HOSP.EDIF.M. | P2482: DIRECCIÓN DE ENFERMERÍA | Q2482: 0 | U2482: 46156
A2483: 394442 | B2483: 54110944V | C2483: GONZALEZ MARTIN, DAMASA TEXENERY | D2483: 46151 | E2483: 46157 | F2483: 179197 | G2483: TEMPORAL. T. COMPLETO. N. ESTATU | H2483: ACUMULACION DE TAREAS | I2483: AUXILIAR DE ENFERMERÍA | J2483: E | K2483: I_9_1c | L2483: N91c | M2483: 7 | N2483: AUXILIAR DE ENFERMERÍA | O2483: PLANTA BAJA - HOSP.EDIF.M. | P2483: DIRECCIÓN DE ENFERMERÍA | Q2483: 0 | U2483: 46157 | V2483: 46387 | W2483: =_xlfn.DAYS(V2483,U2483) -> 230
A2484: 280362 | B2484: 43489869C | C2484: PEREZ GARCIA, CLAUDIA | D2484: 46151 | E2484: 46157 | F2484: 179192 | G2484: TEMPORAL. T. COMPLETO. N. ESTATU | H2484: ACUMULACION DE TAREAS | I2484: ENFERMERO/A | J2484: E | K2484: I_9_1c | L2484: N91c | M2484: 7 | N2484: ENFERMERA/O | O2484: PLANTA BAJA - HOSP.EDIF.M. | P2484: DIRECCIÓN DE ENFERMERÍA | Q2484: 0 | U2484: 46157 | V2484: 46387 | W2484: =_xlfn.DAYS(V2484,U2484) -> 230
A2485: 272907 | B2485: 54049503D | C2485: LUIS RODRIGUEZ, ESTEFANIA | D2485: 46143 | E2485: 46157 | F2485: 0 | G2485: TEMPORAL. T. COMPLETO. N. ESTATU | H2485: ACUMULACION DE TAREAS | I2485: CELADOR/A | J2485: E | K2485: I_9_1c | L2485: N91c | M2485: 15 | N2485: CELADOR | O2485: DISTRIBUCIÓN | P2485: Dirección Servicios Generales | Q2485: 0 | U2485: 46157 | V2485: 46387 | W2485: =_xlfn.DAYS(V2485,U2485) -> 230
A2486: 260402 | B2486: 43797199R | C2486: CORREA GORRIN, MARIA DEL PILAR | D2486: 46143 | E2486: 46157 | F2486: 178783 | G2486: TEMPORAL. T. COMPLETO. N. ESTATU | H2486: ACUMULACION DE TAREAS | I2486: LAVANDERO/A | J2486: E | K2486: I_9_1c | L2486: N91c | M2486: 15 | N2486: LAVANDERIA | O2486: LENCERÍA Y COSTURA | P2486: Dirección Servicios Generales | Q2486: 0 | U2486: 46157 | V2486: 46387 | W2486: =_xlfn.DAYS(V2486,U2486) -> 230
A2487: 236404 | B2487: 45448411C | C2487: DE LEON PEREZ, JUANA ISABEL | D2487: 46143 | E2487: 46157 | F2487: 178786 | G2487: TEMPORAL. T. COMPLETO. N. ESTATU | H2487: ACUMULACION DE TAREAS | I2487: LAVANDERO/A | J2487: E | K2487: I_9_1c | L2487: N91c | M2487: 15 | N2487: LAVANDERIA | O2487: LENCERÍA Y COSTURA | P2487: Dirección Servicios Generales | Q2487: 0 | U2487: 46157 | V2487: 46387 | W2487: =_xlfn.DAYS(V2487,U2487) -> 230
A2488: 255469 | B2488: 79158439Y | C2488: GONZALEZ MONTESINOS, ALEJANDRA | D2488: 46152 | E2488: 46158 | F2488: 179193 | G2488: TEMPORAL. T. COMPLETO. N. ESTATU | H2488: ACUMULACION DE TAREAS | I2488: ENFERMERO/A | J2488: E | K2488: I_9_1c | L2488: N91c | M2488: 7 | N2488: ENFERMERA/O | O2488: PLANTA BAJA - HOSP.EDIF.M. | P2488: DIRECCIÓN DE ENFERMERÍA | Q2488: 0 | U2488: 46158 | V2488: 46387 | W2488: =_xlfn.DAYS(V2488,U2488) -> 229
A2489: 212276 | B2489: 53188053R | C2489: NOGUEIRA MARTINEZ, BRUNO | D2489: 46152 | E2489: 46158 | F2489: 179198 | G2489: TEMPORAL. T. COMPLETO. N. ESTATU | H2489: ACUMULACION DE TAREAS | I2489: AUXILIAR DE ENFERMERÍA | J2489: E | K2489: I_9_1c | L2489: N91c | M2489: 7 | N2489: AUXILIAR DE ENFERMERÍA | O2489: PLANTA BAJA - HOSP.EDIF.M. | P2489: DIRECCIÓN DE ENFERMERÍA | Q2489: 0 | U2489: 46158 | V2489: 46387 | W2489: =_xlfn.DAYS(V2489,U2489) -> 229
A2490: 211111 | B2490: 45451368X | C2490: FERNANDEZ RAMOS, MARIA ANGELES | D2490: 46023 | E2490: 46160 | F2490: 175304 | G2490: TEMPORAL. T. COMPLETO. N. ESTATU | H2490: ACUMULACION DE TAREAS | I2490: PINCHE | J2490: E | K2490: I_9_1c | L2490: N91c | M2490: 138 | N2490: PINCHE | O2490: COCINA | P2490: Dirección Servicios Generales | Q2490: 0 | U2490: 46160 | V2490: 46387 | W2490: =_xlfn.DAYS(V2490,U2490) -> 227
A2491: 265800 | B2491: 51150586N | C2491: LOPEZ SANTANA, ALICIA | D2491: 46023 | E2491: 46166 | F2491: 171667 | G2491: TEMPORAL. T. COMPLETO. N. ESTATU | H2491: ACUMULACION DE TAREAS | I2491: FEA NEUROLOGÍA | J2491: E | K2491: I_9_1c | L2491: N91c | M2491: 144 | N2491: FEA NEUROLOGÍA | O2491: P.MÉDICO NEUROLOGÍA | P2491: DIRECCIÓN MÉDICA | Q2491: 0 | U2491: 46166 | V2491: 46387 | W2491: =_xlfn.DAYS(V2491,U2491) -> 221
A2492: 392088 | B2492: 48774298S | C2492: ROMERO LORENZO, RAQUEL | D2492: 46023 | E2492: 46166 | F2492: 171668 | G2492: TEMPORAL. T. COMPLETO. N. ESTATU | H2492: ACUMULACION DE TAREAS | I2492: FEA NEUROLOGÍA | J2492: E | K2492: I_9_1c | L2492: N91c | M2492: 144 | N2492: FEA NEUROLOGÍA | O2492: P.MÉDICO NEUROLOGÍA | P2492: DIRECCIÓN MÉDICA | Q2492: 0 | U2492: 46166 | V2492: 46387 | W2492: =_xlfn.DAYS(V2492,U2492) -> 221
A2493: 301754 | B2493: 43290003R | C2493: SANCHEZ VIERA, GUADALUPE MARIA NIEVES | D2493: 46023 | E2493: 46167 | F2493: 175484 | G2493: TEMPORAL. T. COMPLETO. N. ESTATU | H2493: ACUMULACION DE TAREAS | I2493: AUXILIAR DE ENFERMERÍA | J2493: E | K2493: I_9_1c | L2493: N91c | M2493: 145 | N2493: AUXILIAR DE ENFERMERÍA | O2493: PLANTA 7ª IMPAR - HOSP.EDIF.A | P2493: DIRECCIÓN DE ENFERMERÍA | Q2493: 0 | U2493: 46167 | V2493: 46387 | W2493: =_xlfn.DAYS(V2493,U2493) -> 220
A2494: 295742 | B2494: 42224484A | C2494: BRITO PACHECO, SHEILA | D2494: 46143 | E2494: 46173 | F2494: 178176 | G2494: TEMPORAL. T. PARCIAL. N. ESTATU. | H2494: ACUMULACION DE TAREAS | I2494: TÉC ESPECIALISTA / RADIODIAGNÓSTICO | J2494: E | K2494: I_9_1c | L2494: N91c | M2494: 31 | N2494: TÉCNICO ESPECIALISTA RADIODIAGNÓSTICO | O2494: AREA.ENFERMERIA - CAE PTO.DE LA CRUZ | P2494: DIRECCIÓN DE ENFERMERÍA | Q2494: 0 | U2494: 46173 | V2494: 46387 | W2494: =_xlfn.DAYS(V2494,U2494) -> 214
...

Sheet Panel
B2: PANEL | G2: RESUMEN DE LA BOLSA NETO
B11: =125215+464271 -> 589486 | D11: =ActivosTotales -> 124526.32 | G11: =PasivosTotales -> 462712.01
B12: BOLSA NETO | D12: Bolsa I91c | G12: Bolsa I9B1a
D13: Dirección Planificación y Gestión RREE | G13: Dirección Planificación y Gestión RREE
D14: Dirección Enfermería | G14: Dirección Enfermería
D15: Dirección Ingeneria, Infraestrutura y Tecn. | G15: Dirección Ingeneria, Infraestrutura y Tecn.
D16: Dirección Servicios Generales | G16: Dirección Servicios Generales
D17: Dirección Médica | G17: Dirección Médica
D18: Dirección RRHH | G18: Dirección RRHH
D19: Gerencia | G19: Gerencia

Sheet I91c
B2: BOLSA I91c | I2: RESUMEN DE LA BOLSA NETO
D4: Bolsa I91c | E4: Tope | I4: Bolsa I91c | J4: Usados | K4: Resto | L4: Necesidad
D5: Gerencia | E5: 1940.8325 | I5: Gerencia | J5: =VLOOKUP(Bolsausados[[#This Row],[Bolsa I91c]],Cálculos!$D$4:$F$10,2,FALSE) -> 5583 | K5: =Bolsatope[[#This Row],[Tope]]-Bolsausados[[#This Row],[Usados]] -> -3642.1675 | L5: =VLOOKUP(Bolsausados[[#This Row],[Bolsa I91c]],Cálculos!$D$4:$F$10,3,FALSE) -> 1744
D6: Dirección Médica | E6: 23289.99 | I6: Dirección Médica | J6: =VLOOKUP(Bolsausados[[#This Row],[Bolsa I91c]],Cálculos!$D$4:$F$10,2,FALSE) -> 33969 | K6: =Bolsatope[[#This Row],[Tope]]-Bolsausados[[#This Row],[Usados]] -> -10679.01 | L6: =VLOOKUP(Bolsausados[[#This Row],[Bolsa I91c]],Cálculos!$D$4:$F$10,3,FALSE) -> 9089
D7: Dirección Enfermería | E7: 76506.365 | I7: DIRECCIÓN DE ENFERMERÍA | J7: =VLOOKUP(Bolsausados[[#This Row],[Bolsa I91c]],Cálculos!$D$4:$F$10,2,FALSE) -> 34607 | K7: =Bolsatope[[#This Row],[Tope]]-Bolsausados[[#This Row],[Usados]] -> 41899.365 | L7: =VLOOKUP(Bolsausados[[#This Row],[Bolsa I91c]],Cálculos!$D$4:$F$10,3,FALSE) -> 18822
D8: Dirección Planificación y Gestión RREE | E8: 6385.965 | I8: Dirección Planificación y Gestión RREE | J8: =VLOOKUP(Bolsausados[[#This Row],[Bolsa I91c]],Cálculos!$D$4:$F$10,2,FALSE) -> 5873 | K8: =Bolsatope[[#This Row],[Tope]]-Bolsausados[[#This Row],[Usados]] -> 512.965 | L8: =VLOOKUP(Bolsausados[[#This Row],[Bolsa I91c]],Cálculos!$D$4:$F$10,3,FALSE) -> 1698
D9: Dirección Ingenería, Infraestructuras y Tecnologías | E9: 3005.16 | I9: Dirección Ingeniería, Infraestructura y Tecnologías | J9: =VLOOKUP(Bolsausados[[#This Row],[Bolsa I91c]],Cálculos!$D$4:$F$10,2,FALSE) -> 8645 | K9: =Bolsatope[[#This Row],[Tope]]-Bolsausados[[#This Row],[Usados]] -> -5639.84 | L9: =VLOOKUP(Bolsausados[[#This Row],[Bolsa I91c]],Cálculos!$D$4:$F$10,3,FALSE) -> 4520
D10: Dirección Servicios Generales | E10: 11394.565 | I10: Dirección Servicios Generales | J10: =VLOOKUP(Bolsausados[[#This Row],[Bolsa I91c]],Cálculos!$D$4:$F$10,2,FALSE) -> 13679 | K10: =Bolsatope[[#This Row],[Tope]]-Bolsausados[[#This Row],[Usados]] -> -2284.435 | L10: =VLOOKUP(Bolsausados[[#This Row],[Bolsa I91c]],Cálculos!$D$4:$F$10,3,FALSE) -> 6317
D11: Dirección RRHH | E11: 2003.44 | I11: DIRECCIÓN DE RR.HH. | J11: =VLOOKUP(Bolsausados[[#This Row],[Bolsa I91c]],Cálculos!$D$4:$F$10,2,FALSE) -> 216 | K11: =Bolsatope[[#This Row],[Tope]]-Bolsausados[[#This Row],[Usados]] -> 1787.44 | L11: =VLOOKUP(Bolsausados[[#This Row],[Bolsa I91c]],Cálculos!$D$4:$F$10,3,FALSE) -> 149
B12: =ActivosTotales -> 124526.32 | D12: SUBTOTAL | E12: =SUBTOTAL(109,Bolsatope[Tope]) -> 124526.32 | I12: SUBTOTAL | J12: =SUBTOTAL(109,Bolsausados[Usados]) -> 102572 | K12: =SUBTOTAL(109,Bolsausados[Resto]) -> 21954.318 | L12: =SUBTOTAL(109,Bolsausados[Necesidad]) -> 42339
B14: ACTIVOS TOTALES
D16: INVERSIONES | E16: VALOR | I16: JUBILACIÓN | J16: VALOR
D17: ACCIONES | E17: 15000 | I17: PENSIÓN
D18: BONOS | I18: CUENTAS IRA
D19: INVERSIONES EN FONDOS MUTUOS | I19: CUENTAS KEOGH
D20: PARTICIPACIONES SOCIALES | I20: 401K | J20: 46000
D21: OTRAS INVERSIONES | I21: SEP
I22: ESOP
D23: SUBTOTAL | E23: =SUBTOTAL(109,tblInversiones[VALOR]) -> 15000 | I23: SUBTOTAL | J23: =SUBTOTAL(109,tblJubilación[VALOR]) -> 46000

Sheet I9B1a
B2: BOLSA I9B1a | H2: RESUMEN DE LA BOLSA NETO
D4: BOLSA I9B1a | E4: Tope | H4: BOLSA I9B1a | I4: Usados | J4: Resto
D5: Gerencia | E5: 7211.7005 | H5: Gerencia | I5: =VLOOKUP(tblAsegurado[[#This Row],[BOLSA I9B1a]],Cálculos!$H$4:$I$10,2,FALSE) -> 2421 | J5: =tblNoAsegurado[[#This Row],[Tope]]-tblAsegurado[[#This Row],[Usados]] -> 4790.7005
D6: Dirección Médica | E6: 86540.406 | H6: Dirección Médica | I6: =VLOOKUP(tblAsegurado[[#This Row],[BOLSA I9B1a]],Cálculos!$H$4:$I$10,2,FALSE) -> 15779 | J6: =tblNoAsegurado[[#This Row],[Tope]]-tblAsegurado[[#This Row],[Usados]] -> 70761.406
D7: Dirección Enfermería | E7: 284280.58 | H7: DIRECCIÓN DE ENFERMERÍA | I7: =VLOOKUP(tblAsegurado[[#This Row],[BOLSA I9B1a]],Cálculos!$H$4:$I$10,2,FALSE) -> 256833 | J7: =tblNoAsegurado[[#This Row],[Tope]]-tblAsegurado[[#This Row],[Usados]] -> 27447.581
D8: Dirección Planificación y Gestión RREE | E8: 23728.821 | H8: Dirección Planificación y Gestión RREE | I8: =VLOOKUP(tblAsegurado[[#This Row],[BOLSA I9B1a]],Cálculos!$H$4:$I$10,2,FALSE) -> 22620 | J8: =tblNoAsegurado[[#This Row],[Tope]]-tblAsegurado[[#This Row],[Usados]] -> 1108.821
D9: Dirección Ingenería, Infraestructuras y Tecnologías | E9: 11166.504 | H9: Dirección Ingeniería, Infraestructura y Tecnologías | I9: =VLOOKUP(tblAsegurado[[#This Row],[BOLSA I9B1a]],Cálculos!$H$4:$I$10,2,FALSE) -> 8028 | J9: =tblNoAsegurado[[#This Row],[Tope]]-tblAsegurado[[#This Row],[Usados]] -> 3138.504
D10: Dirección Servicios Generales | E10: 42339.661 | H10: Dirección Servicios Generales | I10: =VLOOKUP(tblAsegurado[[#This Row],[BOLSA I9B1a]],Cálculos!$H$4:$I$10,2,FALSE) -> 53410 | J10: =tblNoAsegurado[[#This Row],[Tope]]-tblAsegurado[[#This Row],[Usados]] -> -11070.339
D11: Dirección RRHH | E11: 7444.336 | H11: DIRECCIÓN DE RR.HH. | I11: =VLOOKUP(tblAsegurado[[#This Row],[BOLSA I9B1a]],Cálculos!$H$4:$I$10,2,FALSE) -> 4504 | J11: =tblNoAsegurado[[#This Row],[Tope]]-tblAsegurado[[#This Row],[Usados]] -> 2940.336
B12: =PasivosTotales -> 462712.01 | D12: SUBTOTAL | E12: =SUBTOTAL(109,tblNoAsegurado[Tope]) -> 462712.01 | H12: SUBTOTAL | I12: =SUBTOTAL(109,tblAsegurado[Usados]) -> 363595 | J12: =SUBTOTAL(109,tblAsegurado[Resto]) -> 99117.01
B14: ACTIVOS TOTALES

Sheet Cálculos
A1: Bolsa | B1: Tope | D1: T.Nombrto | E1: N91c | H1: T.Nombrto | I1: S9b1a
A2: Gerencia | B2: 1940.8325
A3: Dirección Médica | B3: 23289.99 | D3: Etiquetas de fila | E3: Suma de Días | F3: Suma de Necesidad | H3: Etiquetas de fila | I3: Suma de Días
A4: Dirección Enfermería | B4: 76506.365 | D4: DIRECCIÓN DE ENFERMERÍA | E4: 34607 | F4: 18822 | H4: DIRECCIÓN DE ENFERMERÍA | I4: 256833
A5: Dirección Planificación y Gestión RREE | B5: 6385.965 | D5: DIRECCIÓN DE RR.HH. | E5: 216 | F5: 149 | H5: DIRECCIÓN DE RR.HH. | I5: 4504
A6: Dirección Ingenería, Infraestructuras y Tecnologías | B6: 3005.16 | D6: Dirección Ingeniería, Infraestructura y Tecnologías | E6: 8645 | F6: 4520 | H6: Dirección Ingeniería, Infraestructura y Tecnologías | I6: 8028
A7: Dirección Servicios Generales | B7: 11394.565 | D7: DIRECCIÓN MÉDICA | E7: 33969 | F7: 9089 | H7: DIRECCIÓN MÉDICA | I7: 15779
A8: Dirección RRHH | B8: 2003.44 | D8: Dirección Planificación y Gestión RREE | E8: 5873 | F8: 1698 | H8: Dirección Planificación y Gestión RREE | I8: 22620
A9: SUBTOTAL | B9: 124526.32 | D9: Dirección Servicios Generales | E9: 13679 | F9: 6317 | H9: Dirección Servicios Generales | I9: 53410
D10: GERENCIA | E10: 5583 | F10: 1744 | H10: GERENCIA | I10: 2421
D11: Total general | E11: 102572 | F11: 42339 | H11: Total general | I11: 363595
A14: Bolsa | B14: Tope
A15: I91b | B15: 0
A16: I91c | B16: 125215
A17: I9B1a | B17: 465271
A18: I9B1b | B18: 64
A19: I9B1c | B19: 0
A20: SUBTOTAL | B20: =SUBTOTAL(109,B15:B19) -> 590550
