Workbook
Name ActivosTotales: Cálculos!$B$9
Name Imprimir_Área: [1]Dashboard!$A$1:$H$19
Name PasivosTotales: tblNoAsegurado10[[#Totals],[Tope]]
Name PasivosTotales: tblNoAsegurado[[#Totals],[Tope]]
Name PatrimonioNeto: Cálculos!$B$9

Sheet 2026
A1: NºPer. | B1: Desde* | C1: Hasta* | D1: Necesidad | E1: NºProp. | F1: Nombrto/Contrato | G1: Razón de Alta | H1: Plaza | I1: RJ | J1: Cláusula | K1: T.Nombrto | L1: Días | M1: Días-N | N1: Puesto trabajo | O1: GFH | P1: Dirección | Q1: NºPer.Sust | R1: DNI.Sust | S1: Nombre Sustituido | T1: Puesto Sustitutido | U1: F_Inicio | V1: F_Fin | W1: F_Necesidad
A2: 206656 | B2: 46023 | C2: 46023 | D2: false | E2: 174955 | F2: TEMPORAL. T. COM. INTER. N. ESTA | G2: MES ACTUAL - INCAPACIDAD TEMPORAL | H2: G AUXILIAR ADMINISTRATIVO F. ADMVA | I2: E | J2: S_9B_1A | K2: S9B1A | L2: 1 | M2: 0 | N2: AUXILIAR ADMINISTRATIVO | O2: ALMACÉN DE COMESTIBLES - ECONOMATO | P2: DIRECCIÓN DE SERVICIOS GENERALES | Q2: 363662 | R2: 79063496F | S2: GALVAN ALMENARA, JOSE FERNANDO | T2: AUXILIAR ADMINISTRATIVO | U2: 46023 | V2: 46023 | W2: =(V2-U2)+1 -> 1
A3: 264083 | B3: 46023 | C3: 46023 | D3: false | E3: 175233 | F3: TEMPORAL. T. COM. INTER. N. ESTA | G3: MES ACTUAL - INCAPACIDAD TEMPORAL | H3: AUXILIAR DE ENFERMERÍA | I3: E | J3: S_9B_1A | K3: S9B1A | L3: 1 | M3: 0 | N3: AUXILIAR DE ENFERMERÍA | O3: PLANTA 4ª PAR - HOSP.EDIF.A | P3: DIRECCIÓN DE ENFERMERÍA | Q3: 357307 | R3: 45446641K | S3: VELAZQUEZ GUTIERREZ, EMILIA PILAR | T3: AUXILIAR DE ENFERMERÍA | U3: 46023 | V3: 46023 | W3: =(V3-U3)+1 -> 1
A4: 388396 | B4: 46023 | C4: 46023 | D4: false | E4: 168478 | F4: TEMPORAL. T. COMPLETO. N. ESTATU | G4: ACUMULACION DE TAREAS | H4: FEA CIRUGÍA ORTOPÉDICA Y TRAUMATOLOGÍA | I4: E | J4: I_9_1C | K4: N91C | L4: 1 | M4: 0 | N4: FEA CIRUGÍA ORTOPÉDICA Y TRAUMATOLOGÍA | O4: P.MÉDICO TRAUMA | P4: DIRECCIÓN MÉDICA | Q4: 0 | U4: 46023 | V4: 46023 | W4: =(V4-U4)+1 -> 1
A5: 246568 | B5: 46023 | C5: 46023 | D5: false | E5: 173782 | F5: TEMPORAL. T. COM. INTER. N. ESTA | G5: LIBRE DISPOSICION | H5: LAVANDERO/A | I5: E | J5: S_9B_1AV | K5: S9B1A | L5: 1 | M5: 0 | N5: LAVANDERIA | O5: LAVANDERÍA HOSP.DEL TORAX | P5: DIRECCIÓN DE SERVICIOS GENERALES | Q5: 394450 | R5: 79086389S | S5: GARCIA FRANQUIS, DAVINIA | U5: 46023 | V5: 46023 | W5: =(V5-U5)+1 -> 1
A6: 273291 | B6: 46023 | C6: 46024 | D6: false | E6: 166191 | F6: TEMPORAL. T. COM. INTER. N. ESTA | G6: MES ACTUAL - INCAPACIDAD TEMPORAL | H6: AUXILIAR DE ENFERMERÍA | I6: E | J6: S_9B_1A | K6: S9B1A | L6: 2 | M6: 0 | N6: AUXILIAR DE ENFERMERÍA | O6: PLANTILLA VOLANTE DEL EAA (EDIFICIO DE ACTIVIDADES | P6: DIRECCIÓN DE ENFERMERÍA | Q6: 311907 | R6: 42063809Y | S6: HERRANZ GOMEZ, MARIA CANDELARIA | T6: AUXILIAR DE ENFERMERÍA | U6: 46023 | V6: 46024 | W6: =(V6-U6)+1 -> 2
A7: 271144 | B7: 46023 | C7: 46024 | D7: false | E7: 172724 | F7: TEMPORAL. T. COM. INTER. N. ESTA | G7: MES ACTUAL - INCAPACIDAD TEMPORAL | H7: AUXILIAR DE ENFERMERÍA | I7: E | J7: S_9B_1A | K7: S9B1A | L7: 2 | M7: 0 | N7: AUXILIAR DE ENFERMERÍA | O7: PLANTA 8ª IMPAR - HOSP.EDIF.A | P7: DIRECCIÓN DE ENFERMERÍA | Q7: 298172 | R7: 79354565B | S7: MOYA ZURITA, EVELIN PAMELA | T7: AUXILIAR DE ENFERMERÍA | U7: 46023 | V7: 46024 | W7: =(V7-U7)+1 -> 2
A8: 240038 | B8: 46023 | C8: 46024 | D8: false | E8: 175480 | F8: TEMPORAL. T. COM. INTER. N. ESTA | G8: MES ACTUAL - INCAPACIDAD TEMPORAL | H8: ENFERMERO/A | I8: E | J8: S_9B_1A | K8: S9B1A | L8: 2 | M8: 0 | N8: ENFERMERA/O | O8: U.V.I. | P8: DIRECCIÓN DE ENFERMERÍA | Q8: 351642 | R8: 43824205M | S8: MENDOZA MENDOZA, MARIA JOSE | T8: ENFERMERA/O | U8: 46023 | V8: 46024 | W8: =(V8-U8)+1 -> 2
A9: 295908 | B9: 46023 | C9: 46024 | D9: false | E9: 175310 | F9: TEMPORAL. T. COM. INTER. N. ESTA | G9: MES ACTUAL - INCAPACIDAD TEMPORAL | H9: AUXILIAR DE ENFERMERÍA | I9: E | J9: S_9B_1A | K9: S9B1A | L9: 2 | M9: 0 | N9: AUXILIAR DE ENFERMERÍA | O9: EXPLORAC.NEUROFISIOLOGIA | P9: DIRECCIÓN DE ENFERMERÍA | Q9: 379123 | R9: 78649600L | S9: FERNANDEZ ESPINOZA, ISABEL SARAY | U9: 46023 | V9: 46024 | W9: =(V9-U9)+1 -> 2
A10: 304586 | B10: 46023 | C10: 46024 | D10: false | E10: 173854 | F10: TEMPORAL. T. COM. INTER. N. ESTA | G10: MES ACTUAL - INCAPACIDAD TEMPORAL | H10: AUXILIAR DE ENFERMERÍA | I10: E | J10: S_9B_1A | K10: S9B1A | L10: 2 | M10: 0 | N10: AUXILIAR DE ENFERMERÍA | O10: DIETÉTICA Y NUTRICIÓN | P10: DIRECCIÓN DE ENFERMERÍA | Q10: 290946 | R10: 78625537Z | S10: GUTIERREZ ALONSO, MARIA YURENA | U10: 46023 | V10: 46024 | W10: =(V10-U10)+1 -> 2
A11: 218106 | B11: 46023 | C11: 46024 | D11: false | E11: 175598 | F11: TEMPORAL. T. COM. INTER. N. ESTA | G11: MES ACTUAL - INCAPACIDAD TEMPORAL | H11: LIMPIADOR/A | I11: E | J11: S_9B_1A | K11: S9B1A | L11: 2 | M11: 0 | N11: LIMPIADORA | O11: SUPLENCIAS LIMPIEZA | P11: DIRECCIÓN DE SERVICIOS GENERALES | Q11: 277802 | R11: 43814704A | S11: JAÑEZ JIMENEZ, GEMA | T11: LIMPIADORA | U11: 46023 | V11: 46024 | W11: =(V11-U11)+1 -> 2
A12: 366231 | B12: 46023 | C12: 46024 | D12: false | E12: 173137 | F12: TEMPORAL. T. COM. INTER. N. ESTA | G12: MES ACTUAL - INCAPACIDAD TEMPORAL | H12: ENFERMERO/A | I12: E | J12: S_9B_1A | K12: S9B1A | L12: 2 | M12: 0 | N12: ENFERMERA/O | O12: UNIDAD HOSPITALIZACIÓN A DOMICILIO - HN | P12: DIRECCIÓN DE ENFERMERÍA | Q12: 367396 | R12: 78570327G | S12: MARTIN GARCIA, ANA ISABEL | T12: ENFERMERA/O | U12: 46023 | V12: 46024 | W12: =(V12-U12)+1 -> 2
A13: 278261 | B13: 46023 | C13: 46024 | D13: false | E13: 168561 | F13: TEMPORAL. T. COMPLETO. N. ESTATU | G13: ACUMULACION DE TAREAS | H13: FEA CARDIOLOGÍA | I13: E | J13: I_9_1C | K13: N91C | L13: 2 | M13: 0 | N13: FEA CARDIOLOGÍA | O13: P.MÉDICO CARDIOLOGÍA | P13: DIRECCIÓN MÉDICA | Q13: 0 | U13: 46023 | V13: 46024 | W13: =(V13-U13)+1 -> 2
A14: 265854 | B14: 46023 | C14: 46024 | D14: false | E14: 174158 | F14: TEMPORAL. T. COM. INTER. N. ESTA | G14: MES ACTUAL - INCAPACIDAD TEMPORAL | H14: ENFERMERO/A | I14: E | J14: S_9B_1A | K14: S9B1A | L14: 2 | M14: 0 | N14: ENFERMERA/O | O14: LAB.HEMOT.Y BCO.SANGRE | P14: DIRECCIÓN DE ENFERMERÍA | Q14: 327773 | R14: 78407957Z | S14: MESA SIVERIO, JESUS EULOGIO | T14: ENFERMERA/O | U14: 46023 | V14: 46024 | W14: =(V14-U14)+1 -> 2
A15: 394442 | B15: 46023 | C15: 46024 | D15: false | E15: 175201 | F15: TEMPORAL. T. COM. INTER. N. ESTA | G15: MES ACTUAL - INCAPACIDAD TEMPORAL | H15: AUXILIAR DE ENFERMERÍA | I15: E | J15: S_9B_1A | K15: S9B1A | L15: 2 | M15: 0 | N15: AUXILIAR DE ENFERMERÍA | O15: PLANTA 3ª/4ª URA | P15: DIRECCIÓN DE ENFERMERÍA | Q15: 261451 | R15: 51165292K | S15: PEREZ IZQUIERDO, NEREA | T15: AUXILIAR DE ENFERMERÍA | U15: 46023 | V15: 46024 | W15: =(V15-U15)+1 -> 2
A16: 265414 | B16: 46023 | C16: 46024 | D16: false | E16: 175290 | F16: TEMPORAL. T. COM. INTER. N. ESTA | G16: MES ACTUAL - INCAPACIDAD TEMPORAL | H16: AUXILIAR DE ENFERMERÍA | I16: E | J16: S_9B_1A | K16: S9B1A | L16: 2 | M16: 0 | N16: AUXILIAR DE ENFERMERÍA | O16: PLANTA 4ª - HOSPITALIZACIÓN EDIF. D | P16: DIRECCIÓN DE ENFERMERÍA | Q16: 341732 | R16: 42092314Z | S16: CASTILLO LEON, JOSEFINA | T16: AUXILIAR DE ENFERMERÍA | U16: 46023 | V16: 46024 | W16: =(V16-U16)+1 -> 2
A17: 379807 | B17: 46023 | C17: 46024 | D17: false | E17: 175287 | F17: TEMPORAL. T. COM. INTER. N. ESTA | G17: MES ACTUAL - INCAPACIDAD TEMPORAL | H17: TERAPEUTA OCUPACIONAL | I17: E | J17: S_9B_1A | K17: S9B1A | L17: 2 | M17: 0 | N17: TERAPEUTA OCUPACIONAL | O17: LABORTERAPIA AGUDOS | P17: DIRECCIÓN DE ENFERMERÍA | Q17: 214045 | R17: 74686418J | S17: HURTADO JIMENEZ, ANA ISABEL | T17: TERAPEUTA OCUPACIONAL | U17: 46023 | V17: 46024 | W17: =(V17-U17)+1 -> 2
A18: 246253 | B18: 46023 | C18: 46024 | D18: false | E18: 175220 | F18: TEMPORAL. T. COM. INTER. N. ESTA | G18: MES ACTUAL - INCAPACIDAD TEMPORAL | H18: AUXILIAR DE ENFERMERÍA | I18: E | J18: S_9B_1A | K18: S9B1A | L18: 2 | M18: 0 | N18: AUXILIAR DE ENFERMERÍA | O18: UDAD.HEMODÍALISIS | P18: DIRECCIÓN DE ENFERMERÍA | Q18: 301864 | R18: 42065567Q | S18: HORMIGA ESTRADA, JOSE ANGEL | T18: AUXILIAR DE ENFERMERÍA | U18: 46023 | V18: 46024 | W18: =(V18-U18)+1 -> 2
A19: 268402 | B19: 46023 | C19: 46024 | D19: false | E19: 173951 | F19: TEMPORAL. T. COM. INTER. N. ESTA | G19: VACACIONES Y LIBRANZAS | H19: ENFERMERO/A | I19: E | J19: S_9B_1A | K19: S9B1A | L19: 2 | M19: 0 | N19: ENFERMERA/O | O19: BLOQUE QUIRURGICO CMA | P19: DIRECCIÓN DE ENFERMERÍA | Q19: 318105 | R19: 42083681Y | S19: GUTIERREZ MARQUEZ, MARIA GEMMA | T19: SUPERVISOR/A DE UNIDAD | U19: 46023 | V19: 46024 | W19: =(V19-U19)+1 -> 2
A20: 214420 | B20: 46023 | C20: 46024 | D20: false | E20: 170965 | F20: TEMPORAL. T. COM. INTER. N. ESTA | G20: MES ACTUAL - INCAPACIDAD TEMPORAL | H20: TÉC ESPECIALISTA / LABORATORIO | I20: E | J20: S_9B_1A | K20: S9B1A | L20: 2 | M20: 0 | N20: TÉCNICO ESPECIALISTA LABORATORIO | O20: LABORATORIO CENTRAL | P20: DIRECCIÓN DE ENFERMERÍA | Q20: 339002 | R20: 43821293Z | S20: JORGE ARTEAGA, MARIA JESUS | T20: TÉCNICO ESPECIALISTA LABORATORIO | U20: 46023 | V20: 46024 | W20: =(V20-U20)+1 -> 2
A21: 305467 | B21: 46023 | C21: 46024 | D21: false | E21: 175446 | F21: TEMPORAL. T. COM. INTER. N. ESTA | G21: MES ACTUAL - INCAPACIDAD TEMPORAL | H21: AUXILIAR DE ENFERMERÍA | I21: E | J21: S_9B_1A | K21: S9B1A | L21: 2 | M21: 0 | N21: AUXILIAR DE ENFERMERÍA | O21: PLANTA 1ª - HOSPITALIZACIÓN EDIF. D | P21: DIRECCIÓN DE ENFERMERÍA | Q21: 367978 | R21: 78859096P | S21: RODRIGUES AFONSO, ROSILENE | T21: AUXILIAR DE ENFERMERÍA | U21: 46023 | V21: 46024 | W21: =(V21-U21)+1 -> 2
A22: 261451 | B22: 46023 | C22: 46024 | D22: false | E22: 174898 | F22: TEMPORAL. T. COM. INTER. N. ESTA | G22: MES ACTUAL - INCAPACIDAD TEMPORAL | H22: AUXILIAR DE ENFERMERÍA | I22: E | J22: S_9B_1A | K22: S9B1A | L22: 2 | M22: 0 | N22: AUXILIAR DE ENFERMERÍA | O22: PLANTA 3ª/4ª URA | P22: DIRECCIÓN DE ENFERMERÍA | Q22: 241702 | R22: 42191242L | S22: PEREZ LORENZO, NIRA | T22: AUXILIAR DE ENFERMERÍA | U22: 46023 | V22: 46024 | W22: =(V22-U22)+1 -> 2
A23: 229155 | B23: 46023 | C23: 46026 | D23: false | E23: 174984 | F23: TEMPORAL. T. COMPLETO. N. ESTATU | G23: ACUMULACION DE TAREAS | H23: TÉC ESPECIALISTA / RADIODIAGNÓSTICO | I23: E | J23: I_9_1C | K23: N91C | L23: 4 | M23: 0 | N23: TÉCNICO ESPECIALISTA RADIODIAGNÓSTICO | O23: RADIODIAGNOSTICO | P23: DIRECCIÓN DE ENFERMERÍA | Q23: 0 | U23: 46023 | V23: 46026 | W23: =(V23-U23)+1 -> 4
A24: 354274 | B24: 46023 | C24: 46026 | D24: false | E24: 170287 | F24: TEMPORAL. T. COM. INTER. N. ESTA | G24: MES ACTUAL - INCAPACIDAD TEMPORAL | H24: LIMPIADOR/A | I24: E | J24: S_9B_1A | K24: S9B1A | L24: 4 | M24: 0 | N24: LIMPIADORA | O24: LIMPIEZA | P24: DIRECCIÓN DE SERVICIOS GENERALES | Q24: 256125 | R24: 42220411R | S24: CASTRO FERNANDEZ, YVONNE | T24: LIMPIADORA | U24: 46023 | V24: 46026 | W24: =(V24-U24)+1 -> 4
A25: 203345 | B25: 46023 | C25: 46026 | D25: false | E25: 173002 | F25: TEMPORAL. T. COM. INTER. N. ESTA | G25: MES ACTUAL - INCAPACIDAD TEMPORAL | H25: AUXILIAR DE ENFERMERÍA | I25: E | J25: S_9B_1A | K25: S9B1A | L25: 4 | M25: 0 | N25: AUXILIAR DE ENFERMERÍA | O25: PLANTA 1ª PAR - HOSP.EDIF.A | P25: DIRECCIÓN DE ENFERMERÍA | Q25: 304894 | R25: 78639822Q | S25: VILLA ROMERO, LORENA | T25: AUXILIAR DE ENFERMERÍA | U25: 46023 | V25: 46026 | W25: =(V25-U25)+1 -> 4
A26: 334213 | B26: 46023 | C26: 46027 | D26: false | E26: 173779 | F26: TEMPORAL. T. COM. INTER. N. ESTA | G26: MES ACTUAL - INCAPACIDAD TEMPORAL | H26: AUXILIAR DE ENFERMERÍA | I26: E | J26: S_9B_1A | K26: S9B1A | L26: 5 | M26: 0 | N26: AUXILIAR DE ENFERMERÍA | O26: PLANTILLA VOLANTE DEL EAA (EDIFICIO DE ACTIVIDADES | P26: DIRECCIÓN DE ENFERMERÍA | Q26: 353760 | R26: 43808780J | S26: ALONSO CARBALLO, CANDELARIA DACIL | T26: AUXILIAR DE ENFERMERÍA | U26: 46023 | V26: 46027 | W26: =(V26-U26)+1 -> 5
A27: 249715 | B27: 46023 | C27: 46027 | D27: false | E27: 173835 | F27: TEMPORAL. T. COM. INTER. N. ESTA | G27: MES ACTUAL - INCAPACIDAD TEMPORAL | H27: AUXILIAR DE ENFERMERÍA | I27: E | J27: S_9B_1A | K27: S9B1A | L27: 5 | M27: 0 | N27: AUXILIAR DE ENFERMERÍA | O27: PLANTA 1ª PAR - HOSP.EDIF.A | P27: DIRECCIÓN DE ENFERMERÍA | Q27: 222124 | R27: 45457791Q | S27: DE DIOS FAGUNDO, MARIA ALEJANDRA | T27: AUXILIAR DE ENFERMERÍA | U27: 46023 | V27: 46027 | W27: =(V27-U27)+1 -> 5
A28: 341254 | B28: 46023 | C28: 46027 | D28: false | E28: 175603 | F28: TEMPORAL. T. COM. INTER. N. ESTA | G28: MES ACTUAL - INCAPACIDAD TEMPORAL | H28: AUXILIAR DE ENFERMERÍA | I28: E | J28: S_9B_1A | K28: S9B1A | L28: 5 | M28: 0 | N28: AUXILIAR DE ENFERMERÍA | O28: URGENCIAS | P28: DIRECCIÓN DE ENFERMERÍA | Q28: 295509 | R28: 54054030M | S28: BAJET FERNANDEZ-ARDISANA, PATRICIA | T28: AUXILIAR DE ENFERMERÍA | U28: 46023 | V28: 46027 | W28: =(V28-U28)+1 -> 5
A29: 222124 | B29: 46023 | C29: 46027 | D29: false | E29: 169667 | F29: TEMPORAL. T. COM. INTER. N. ESTA | G29: MES ACTUAL - INCAPACIDAD TEMPORAL | H29: AUXILIAR DE ENFERMERÍA | I29: E | J29: S_9B_1A | K29: S9B1A | L29: 5 | M29: 0 | N29: AUXILIAR DE ENFERMERÍA | O29: PLANTA 1ª PAR - HOSP.EDIF.A | P29: DIRECCIÓN DE ENFERMERÍA | Q29: 247525 | R29: 45456181Q | S29: CAMPO DIAZ LEDESMA, MARIA ADELA | T29: AUXILIAR DE ENFERMERÍA | U29: 46023 | V29: 46027 | W29: =(V29-U29)+1 -> 5
A30: 251854 | B30: 46023 | C30: 46027 | D30: false | E30: 173723 | F30: TEMPORAL. T. COM. INTER. N. ESTA | G30: MES ACTUAL - INCAPACIDAD TEMPORAL | H30: AUXILIAR DE ENFERMERÍA | I30: E | J30: S_9B_1A | K30: S9B1A | L30: 5 | M30: 0 | N30: AUXILIAR DE ENFERMERÍA | O30: ESTERILIZACIÓN | P30: DIRECCIÓN DE ENFERMERÍA | Q30: 380974 | R30: 45444569L | S30: GAMEZ RAMOS, MARIA AUXILIADORA | T30: AUXILIAR DE ENFERMERÍA | U30: 46023 | V30: 46027 | W30: =(V30-U30)+1 -> 5
A31: 376058 | B31: 46023 | C31: 46027 | D31: false | E31: 173126 | F31: TEMPORAL. T. COM. INTER. N. ESTA | G31: MES ACTUAL - INCAPACIDAD TEMPORAL | H31: ENFERMERO/A | I31: E | J31: S_9B_1A | K31: S9B1A | L31: 5 | M31: 0 | N31: ENFERMERA/O | O31: PLANTA 7ª PAR - HOSP.EDIF.A | P31: DIRECCIÓN DE ENFERMERÍA | Q31: 367572 | R31: 78628266Y | S31: RUIZ MESA, LOURDES | T31: ENFERMERA/O | U31: 46023 | V31: 46027 | W31: =(V31-U31)+1 -> 5
A32: 296095 | B32: 46023 | C32: 46027 | D32: false | E32: 173657 | F32: TEMPORAL. T. COM. INTER. N. ESTA | G32: MES ACTUAL - INCAPACIDAD TEMPORAL | H32: ENFERMERO/A | I32: E | J32: S_9B_1A | K32: S9B1A | L32: 5 | M32: 0 | N32: ENFERMERA/O | O32: PLANTA 1ª - HOSPITALIZACIÓN EDIF. D | P32: DIRECCIÓN DE ENFERMERÍA | Q32: 339758 | R32: 78673312H | S32: ALVARO AFONSO, MARIA DE LA O | T32: SUPERVISOR/A DE UNIDAD | U32: 46023 | V32: 46027 | W32: =(V32-U32)+1 -> 5
A33: 265414 | B33: 46025 | C33: 46027 | D33: false | E33: 175639 | F33: TEMPORAL. T. COM. INTER. N. ESTA | G33: LIBRE DISPOSICION | H33: AUXILIAR DE ENFERMERÍA | I33: E | J33: S_9B_1A | K33: S9B1A | L33: 3 | M33: 0 | N33: AUXILIAR DE ENFERMERÍA | O33: PLANTA 4ª - HOSPITALIZACIÓN EDIF. D | P33: DIRECCIÓN DE ENFERMERÍA | Q33: 345867 | R33: 78613215C | S33: HERNANDEZ RODRIGUEZ, RAQUEL | T33: AUXILIAR DE ENFERMERÍA | U33: 46025 | V33: 46027 | W33: =(V33-U33)+1 -> 3
A34: 371650 | B34: 46023 | C34: 46028 | D34: false | E34: 173860 | F34: TEMPORAL. T. COM. INTER. N. ESTA | G34: LIBRE DISPOSICION | H34: G ADMINISTRATIVO FUNCIÓN ADMINISTRATIVA | I34: E | J34: S_9B_1AV | K34: S9B1A | L34: 6 | M34: 0 | N34: GRUPO ADMINISTRATIVO | O34: COORDINACIÓN DE INFORMACIÓN | P34: GERENCIA | Q34: 294757 | R34: 42221194W | S34: GONZALEZ VIERA, VERONICA | T34: GRUPO ADMINISTRATIVO | U34: 46023 | V34: 46028 | W34: =(V34-U34)+1 -> 6
A35: 209704 | B35: 46023 | C35: 46028 | D35: false | E35: 163552 | F35: TEMPORAL. T. COM. INTER. N. ESTA | G35: MES ACTUAL - INCAPACIDAD TEMPORAL | H35: COCINERO/A | I35: E | J35: S_9B_1A | K35: S9B1A | L35: 6 | M35: 0 | N35: COCINERO | O35: COCINA | P35: DIRECCIÓN DE SERVICIOS GENERALES | Q35: 373710 | R35: 78569848P | S35: SABINA PEREZ, GUILLERMO MARINO | T35: COCINERO | U35: 46023 | V35: 46028 | W35: =(V35-U35)+1 -> 6
... A44: 201947 | B44: 46023 | C44: 46029 | D44: false | E44: 175066 | F44: TEMPORAL. T. COM. INTER. N. ESTA | G44: MES ACTUAL - INCAPACIDAD TEMPORAL | H44: AUXILIAR DE ENFERMERÍA | I44: E | J44: S_9B_1A | K44: S9B1A | L44: 7 | M44: 0 | N44: AUXILIAR DE ENFERMERÍA | O44: PLANTA 2ª - HOSPITAL DEL NORTE | P44: DIRECCIÓN DE ENFERMERÍA | Q44: 359361 | R44: 78612195N | S44: GARCIA GONZALEZ, MARIA ANGELES | T44: AUXILIAR DE ENFERMERÍA | U44: 46023 | V44: 46029 | W44: =(V44-U44)+1 -> 7
A45: 330563 | B45: 46023 | C45: 46029 | D45: false | E45: 168560 | F45: TEMPORAL. T. COMPLETO. N. ESTATU | G45: ACUMULACION DE TAREAS | H45: FEA HEMATOLOGÍA Y HEMOTERAPIA | I45: E | J45: I_9_1C | K45: N91C | L45: 7 | M45: 0 | N45: FEA HEMATOLOGÍA Y HEMOTERAPIA | O45: P.MÉDICO HEMATOLOGÍA CLÍNICA | P45: DIRECCIÓN MÉDICA | Q45: 0 | U45: 46023 | V45: 46029 | W45: =(V45-U45)+1 -> 7
A46: 278362 | B46: 46023 | C46: 46029 | D46: false | E46: 174770 | F46: TEMPORAL. T. COM. INTER. N. ESTA | H46: AUXILIAR DE ENFERMERÍA | I46: E | J46: S_9B_1A | K46: S9B1A | L46: 7 | M46: 0 | N46: AUXILIAR DE ENFERMERÍA | O46: PLANTA 2ª CENTRAL A - EDIF.B | P46: DIRECCIÓN DE ENFERMERÍA | Q46: 365390 | R46: 78620644C | S46: BELTRAN DORTA, VERONICA | T46: AUXILIAR DE ENFERMERÍA | U46: 46023 | V46: 46029 | W46: =(V46-U46)+1 -> 7
A47: 229806 | B47: 46023 | C47: 46029 | D47: false | E47: 175328 | F47: TEMPORAL. T. COM. INTER. N. ESTA | G47: MES ACTUAL - INCAPACIDAD TEMPORAL | H47: AUXILIAR DE ENFERMERÍA | I47: E | J47: S_9B_1A | K47: S9B1A | L47: 7 | M47: 0 | N47: AUXILIAR DE ENFERMERÍA | O47: UDAD.SALUD MENTAL DE TACORONTE | P47: DIRECCIÓN DE ENFERMERÍA | Q47: 224380 | R47: 42093891G | S47: ROSA GONZALEZ, LIDIA | T47: AUXILIAR DE ENFERMERÍA | U47: 46023 | V47: 46029 | W47: =(V47-U47)+1 -> 7
A48: 206974 | B48: 46023 | C48: 46029 | D48: false | E48: 175049 | F48: TEMPORAL. T. COM. INTER. N. ESTA | G48: MES ACTUAL - INCAPACIDAD TEMPORAL | H48: AUXILIAR DE ENFERMERÍA | I48: E | J48: S_9B_1A | K48: S9B1A | L48: 7 | M48: 0 | N48: AUXILIAR DE ENFERMERÍA | O48: RADIODIAGNOSTICO | P48: DIRECCIÓN DE ENFERMERÍA | Q48: 382786 | R48: 54061526A | S48: MORENO GONZALEZ, DESIREE | T48: AUXILIAR DE ENFERMERÍA | U48: 46023 | V48: 46029 | W48: =(V48-U48)+1 -> 7
A49: 309907 | B49: 46023 | C49: 46029 | D49: false | E49: 174760 | F49: TEMPORAL. T. COMPLETO. N. ESTATU | G49: ACUMULACION DE TAREAS | H49: G AUXILIAR ADMINISTRATIVO F. ADMVA | I49: E | J49: I_9_1C | K49: N91C | L49: 7 | M49: 0 | N49: AUXILIAR ADMINISTRATIVO | O49: ARCHIVO CENTRAL | P49: DIRECCIÓN DE PLANIFIFCACIÓN Y GESTIÓN DE RR.EE. | Q49: 0 | U49: 46023 | V49: 46029 | W49: =(V49-U49)+1 -> 7
A50: 252647 | B50: 46023 | C50: 46029 | D50: false | E50: 174222 | F50: TEMPORAL. T. COM. INTER. N. ESTA | G50: MES ACTUAL - INCAPACIDAD TEMPORAL | H50: AUXILIAR DE ENFERMERÍA | I50: E | J50: S_9B_1A | K50: S9B1A | L50: 7 | M50: 0 | N50: AUXILIAR DE ENFERMERÍA | O50: URGENCIAS | P50: DIRECCIÓN DE ENFERMERÍA | Q50: 381003 | R50: 43781158Z | S50: MONTSERRAT DENIZ, GONZALO | T50: AUXILIAR DE ENFERMERÍA | U50: 46023 | V50: 46029 | W50: =(V50-U50)+1 -> 7
A51: 228080 | B51: 46023 | C51: 46029 | D51: false | E51: 170872 | F51: TEMPORAL. T. COM. INTER. N. ESTA | G51: MES ACTUAL - INCAPACIDAD TEMPORAL | H51: AUXILIAR DE ENFERMERÍA | I51: E | J51: S_9B_1A | K51: S9B1A | L51: 7 | M51: 0 | N51: AUXILIAR DE ENFERMERÍA | O51: URGENCIAS | P51: DIRECCIÓN DE ENFERMERÍA | Q51: 310715 | R51: 42076082C | S51: MACHADO MACHADO, JUDITH | T51: AUXILIAR DE ENFERMERÍA | U51: 46023 | V51: 46029 | W51: =(V51-U51)+1 -> 7
A52: 398286 | B52: 46023 | C52: 46029 | D52: false | E52: 174475 | F52: TEMPORAL. T. COM. INTER. N. ESTA | G52: LIBRE DISPOSICION | H52: TELEFONISTA | I52: E | J52: S_9B_1AV | K52: S9B1A | L52: 7 | M52: 0 | N52: TELEFONISTA | O52: TELEFONISTAS | P52: DIRECCIÓN DE SERVICIOS GENERALES | Q52: 367345 | R52: 45444101B | S52: GONZALEZ HERNANDEZ, MARIA LUZ | T52: TELEFONISTA | U52: 46023 | V52: 46029 | W52: =(V52-U52)+1 -> 7
A53: 272740 | B53: 46023 | C53: 46029 | D53: false | E53: 168889 | F53: TEMPORAL. T. COM. INTER. N. ESTA | G53: MES ACTUAL - INCAPACIDAD TEMPORAL | H53: LAVANDERO/A | I53: E | J53: S_9B_1A | K53: S9B1A | L53: 7 | M53: 0 | N53: LAVANDERIA | O53: LAVANDERÍA HOSP.DEL TORAX | P53: DIRECCIÓN DE SERVICIOS GENERALES | Q53: 265596 | R53: 52820914B | S53: AFONSO GONZALEZ, NICOL | T53: LAVANDERIA | U53: 46023 | V53: 46029 | W53: =(V53-U53)+1 -> 7
A54: 246253 | B54: 46025 | C54: 46029 | D54: false | E54: 175609 | F54: TEMPORAL. T. COM. INTER. N. ESTA | G54: MES ACTUAL - INCAPACIDAD TEMPORAL | H54: AUXILIAR DE ENFERMERÍA | I54: E | J54: S_9B_1A | K54: S9B1A | L54: 5 | M54: 0 | N54: AUXILIAR DE ENFERMERÍA | O54: PLANTA 6ª PAR - HOSP.EDIF.A | P54: DIRECCIÓN DE ENFERMERÍA | Q54: 370237 | R54: 43819848H | S54: NAVARRO SANCHEZ, NURIA | T54: AUXILIAR DE ENFERMERÍA | U54: 46025 | V54: 46029 | W54: =(V54-U54)+1 -> 5
A55: 334213 | B55: 46029 | C55: 46029 | D55: false | E55: 175662 | F55: TEMPORAL. T. COM. INTER. N. ESTA | G55: LIBRE DISPOSICION | H55: AUXILIAR DE ENFERMERÍA | I55: E | J55: S_9B_1A | K55: S9B1A | L55: 1 | M55: 0 | N55: AUXILIAR DE ENFERMERÍA | O55: PLANTILLA VOLANTE DEL EAA (EDIFICIO DE ACTIVIDADES | P55: DIRECCIÓN DE ENFERMERÍA | Q55: 219491 | R55: 79060248W | S55: HERNANDEZ BARRIOS, SARA | T55: AUXILIAR DE ENFERMERÍA | U55: 46029 | V55: 46029 | W55: =(V55-U55)+1 -> 1
A56: 274993 | B56: 46029 | C56: 46029 | D56: false | E56: 175632 | F56: TEMPORAL. T. COM. INTER. N. ESTA | G56: LIBRE DISPOSICION | H56: TÉC ESPECIALISTA / DIETETICA Y NUTRICION | I56: E | J56: S_9B_1A | K56: S9B1A | L56: 1 | M56: 0 | N56: TÉCNICO ESPECIALISTA EN DIETÉTICA Y NUTRICIÓN | O56: DIETÉTICA Y NUTRICIÓN | P56: DIRECCIÓN DE ENFERMERÍA | Q56: 317305 | R56: 42090581Y | S56: BATISTA NEGRIN, VICTORIA CANDELARIA | T56: TÉCNICO ESPECIALISTA EN DIETÉTICA Y NUTRICIÓN | U56: 46029 | V56: 46029 | W56: =(V56-U56)+1 -> 1
A57: 203721 | B57: 46023 | C57: 46030 | D57: false | E57: 175617 | F57: TEMPORAL. T. COM. INTER. N. ESTA | G57: MES ACTUAL - INCAPACIDAD TEMPORAL | H57: LIMPIADOR/A | I57: E | J57: S_9B_1A | K57: S9B1A | L57: 8 | M57: 0 | N57: LIMPIADORA | O57: LIMPIEZA | P57: DIRECCIÓN DE SERVICIOS GENERALES | Q57: 208933 | R57: 78729092T | S57: RAMOS PLASENCIA, JOANAN AROE | T57: LIMPIADORA | U57: 46023 | V57: 46030 | W57: =(V57-U57)+1 -> 8
A58: 296954 | B58: 46023 | C58: 46030 | D58: false | E58: 173859 | F58: TEMPORAL. T. COM. INTER. N. ESTA | G58: LIBRE DISPOSICION | H58: G ADMINISTRATIVO FUNCIÓN ADMINISTRATIVA | I58: E | J58: S_9B_1AV | K58: S9B1A | L58: 8 | M58: 0 | N58: GRUPO ADMINISTRATIVO | O58: COORDINACIÓN DE INFORMACIÓN | P58: GERENCIA | Q58: 311085 | R58: 42066932R | S58: HERNANDEZ LUJAN, FATIMA | T58: TÉCNICO DE ATENCIÓN AL USUARIO | U58: 46023 | V58: 46030 | W58: =(V58-U58)+1 -> 8
A59: 356815 | B59: 46023 | C59: 46030 | D59: false | E59: 175584 | F59: TEMPORAL. T. COM. INTER. N. ESTA | G59: MES ACTUAL - INCAPACIDAD TEMPORAL | H59: TÉC ESPECIALISTA / LABORATORIO | I59: E | J59: S_9B_1A | K59: S9B1A | L59: 8 | M59: 0 | N59: TÉCNICO ESPECIALISTA LABORATORIO | O59: LABOR.DE MICROBIOLOGIA Y CONTROL DE INF | P59: DIRECCIÓN DE ENFERMERÍA | Q59: 353995 | R59: 78404595X | S59: HERNANDEZ PLASENCIA, LUISA ESTHER | T59: TÉCNICO ESPECIALISTA LABORATORIO | U59: 46023 | V59: 46030 | W59: =(V59-U59)+1 -> 8
A60: 398139 | B60: 46023 | C60: 46030 | D60: false | E60: 173912 | F60: TEMPORAL. T. COM. INTER. N. ESTA | G60: LIBRE DISPOSICION | H60: TÉC ESPECIALISTA / RADIODIAGNÓSTICO | I60: E | J60: S_9B_1A | K60: S9B1A | L60: 8 | M60: 0 | N60: TÉCNICO ESPECIALISTA RADIODIAGNÓSTICO | O60: AREA.ENFERMERIA - CAE LA LAGUNA-GENETO | P60: DIRECCIÓN DE ENFERMERÍA | Q60: 361373 | R60: 78693883G | S60: GARCIA HERNANDEZ, JASMINA | T60: TÉCNICO ESPECIALISTA RADIODIAGNÓSTICO | U60: 46023 | V60: 46030 | W60: =(V60-U60)+1 -> 8
A61: 272848 | B61: 46023 | C61: 46030 | D61: false | E61: 175448 | F61: TEMPORAL. T. COM. INTER. N. ESTA | G61: MES ACTUAL - INCAPACIDAD TEMPORAL | H61: AUXILIAR DE ENFERMERÍA | I61: E | J61: S_9B_1A | K61: S9B1A | L61: 8 | M61: 0 | N61: AUXILIAR DE ENFERMERÍA | O61: PLANTA 10ª PAR - HOSP.EDIF.A | P61: DIRECCIÓN DE ENFERMERÍA | Q61: 366203 | R61: 79065777B | S61: CERCADO VILLALOBOS, RICCI DORIS | T61: AUXILIAR DE ENFERMERÍA | U61: 46023 | V61: 46030 | W61: =(V61-U61)+1 -> 8
... A80: 345847 | B80: 46028 | C80: 46031 | D80: false | E80: 175634 | F80: TEMPORAL. T. COM. INTER. N. ESTA | G80: MES VENCIDO - INCAPACIDAD TEMPORAL | H80: ENFERMERO/A | I80: E | J80: S_9B_1A | K80: S9B1A | L80: 4 | M80: 0 | N80: ENFERMERA/O | O80: URGENCIAS | P80: DIRECCIÓN DE ENFERMERÍA | Q80: 224602 | R80: 79088771M | S80: MARTIN NEGI, AIRAM | T80: ENFERMERA/O | U80: 46028 | V80: 46031 | W80: =(V80-U80)+1 -> 4
A81: 217553 | B81: 46030 | C81: 46031 | D81: false | E81: 175354 | F81: TEMPORAL. T. COM. INTER. N. ESTA | G81: GUARDIAS AT.CONTINUADA | H81: FEA NEFROLOGÍA | I81: E | J81: S_9B_1BG | K81: S9B1B | L81: 2 | M81: 0 | N81: FEA NEFROLOGÍA | O81: P.MÉDICO NEFROLOGÍA | P81: DIRECCIÓN MÉDICA | Q81: 0 | U81: 46030 | V81: 46031 | W81: =(V81-U81)+1 -> 2
A82: 334213 | B82: 46030 | C82: 46031 | D82: false | E82: 175635 | F82: TEMPORAL. T. COM. INTER. N. ESTA | G82: MES VENCIDO - INCAPACIDAD TEMPORAL | H82: AUXILIAR DE ENFERMERÍA | I82: E | J82: S_9B_1A | K82: S9B1A | L82: 2 | M82: 0 | N82: AUXILIAR DE ENFERMERÍA | O82: URGENCIAS | P82: DIRECCIÓN DE ENFERMERÍA | Q82: 382837 | R82: 54050178V | S82: HERNANDEZ SANTANA, MONTSERRAT | T82: AUXILIAR DE ENFERMERÍA | U82: 46030 | V82: 46031 | W82: =(V82-U82)+1 -> 2
A83: 349426 | B83: 46023 | C83: 46033 | D83: false | E83: 169719 | F83: TEMPORAL. T. COM. INTER. N. ESTA | G83: INTERINO POR VACANTE | H83: FEA NEUMOLOGÍA | I83: E | J83: I_9_1A | K83: N91A | L83: 11 | M83: 0 | N83: FEA NEUMOLOGÍA | O83: P.MÉDICO NEUMOLOGÍA | P83: DIRECCIÓN MÉDICA | Q83: 0 | U83: 46023 | V83: 46033 | W83: =(V83-U83)+1 -> 11
A84: 321835 | B84: 46023 | C84: 46033 | D84: false | E84: 173291 | F84: TEMPORAL. T. COM. INTER. N. ESTA | G84: REDUCCION DE JORNADA | H84: ENFERMERO/A | I84: E | J84: S_9B_1C | K84: S9B1C | L84: 11 | M84: 0 | N84: ENFERMERA/O | O84: URGENCIAS | P84: DIRECCIÓN DE ENFERMERÍA | Q84: 354966 | R84: 78559081M | S84: LOPEZ RAVELO, MARIA DE LA CONCEPCION | T84: ENFERMERA/O | U84: 46023 | V84: 46033 | W84: =(V84-U84)+1 -> 11
A85: 321549 | B85: 46023 | C85: 46033 | D85: false | E85: 172258 | F85: TEMPORAL. T. COM. INTER. N. ESTA | G85: MES VENCIDO - INCAPACIDAD TEMPORAL | H85: ENFERMERO/A | I85: E | J85: S_9B_1A | K85: S9B1A | L85: 11 | M85: 0 | N85: ENFERMERA/O | O85: PLANTA BAJA - HOSP.EDIF.M. | P85: DIRECCIÓN DE ENFERMERÍA | Q85: 239390 | R85: 79088275S | S85: NESTARES DURAN, NOHELIA ELIZABETH | T85: ENFERMERA/O | U85: 46023 | V85: 46033 | W85: =(V85-U85)+1 -> 11
A86: 255923 | B86: 46023 | C86: 46033 | D86: false | E86: 173907 | F86: TEMPORAL. T. COM. INTER. N. ESTA | G86: REDUCCION DE JORNADA | H86: ENFERMERO/A | I86: E | J86: S_9B_1C | K86: S9B1C | L86: 11 | M86: 0 | N86: ENFERMERA/O | O86: UDES.ESPECIALES SUPLENCIAS | P86: DIRECCIÓN DE ENFERMERÍA | Q86: 362579 | R86: 78705028V | S86: CORREA VENTURA, NIEVES BEATRIZ | T86: ENFERMERA/O | U86: 46023 | V86: 46033 | W86: =(V86-U86)+1 -> 11
A87: 389597 | B87: 46023 | C87: 46033 | D87: false | E87: 152987 | F87: TEMPORAL. T. COM. INTER. N. ESTA | G87: INTERINO POR VACANTE | H87: FEA NEUMOLOGÍA | I87: E | J87: I_9_1A | K87: N91A | L87: 11 | M87: 0 | N87: FEA NEUMOLOGÍA | O87: P.MÉDICO NEUMOLOGÍA | P87: DIRECCIÓN MÉDICA | Q87: 0 | U87: 46023 | V87: 46033 | W87: =(V87-U87)+1 -> 11
A88: 160888 | B88: 46023 | C88: 46033 | D88: false | E88: 169690 | F88: TEMPORAL. T. COM. INTER. N. ESTA | G88: INTERINO POR VACANTE | H88: FEA ENDOCRINOLOGÍA Y N | I88: E | J88: I_9_1A | K88: N91A | L88: 11 | M88: 0 | N88: FEA ENDOCRINOLOGÍA Y NUTRICIÓN | O88: P.MÉDICO ENDOCRINOLOGÍA | P88: DIRECCIÓN MÉDICA | Q88: 0 | U88: 46023 | V88: 46033 | W88: =(V88-U88)+1 -> 11
A89: 294431 | B89: 46023 | C89: 46033 | D89: false | E89: 173857 | F89: TEMPORAL. T. COM. INTER. N. ESTA | G89: LIBRE DISPOSICION | H89: G ADMINISTRATIVO FUNCIÓN ADMINISTRATIVA | I89: E | J89: S_9B_1AV | K89: S9B1A | L89: 11 | M89: 0 | N89: GRUPO ADMINISTRATIVO | O89: COORDINACIÓN DE INFORMACIÓN | P89: GERENCIA | Q89: 208261 | R89: 42089334R | S89: PEREZ SANTIAGO, ANA MARIA | T89: TÉCNICO DE ATENCIÓN AL USUARIO | U89: 46023 | V89: 46033 | W89: =(V89-U89)+1 -> 11
A90: 187533 | B90: 46023 | C90: 46033 | D90: false | E90: 153022 | F90: TEMPORAL. T. COM. INTER. N. ESTA | G90: INTERINO POR VACANTE | H90: MEDICO/A URGENCIA HOSPITALARIA | I90: E | J90: I_9_1A | K90: N91A | L90: 11 | M90: 0 | N90: MÉDICO URGENCIA HOSPITALARIA | O90: P.MÉDICO GERIATRÍA HOSP.NORTE | P90: DIRECCIÓN MÉDICA | Q90: 0 | U90: 46023 | V90: 46033 | W90: =(V90-U90)+1 -> 11
A91: 229588 | B91: 46023 | C91: 46033 | D91: false | E91: 169720 | F91: TEMPORAL. T. COM. INTER. N. ESTA | G91: INTERINO POR VACANTE | H91: FEA NEUMOLOGÍA | I91: E | J91: I_9_1A | K91: N91A | L91: 11 | M91: 0 | N91: FEA NEUMOLOGÍA | O91: P.MÉDICO NEUMOLOGÍA | P91: DIRECCIÓN MÉDICA | Q91: 0 | U91: 46023 | V91: 46033 | W91: =(V91-U91)+1 -> 11
A92: 279510 | B92: 46023 | C92: 46033 | D92: false | E92: 168730 | F92: TEMPORAL. T. COM. INTER. N. ESTA | G92: LACTANCIA | H92: ENFERMERO/A | I92: E | J92: S_9B_1A | K92: S9B1A | L92: 11 | M92: 0 | N92: ENFERMERA/O | O92: UDAD.CORONARIAS | P92: DIRECCIÓN DE ENFERMERÍA | Q92: 367484 | R92: 54059159M | S92: DIAZ FLORES, MELISA JANET | T92: ENFERMERA/O | U92: 46023 | V92: 46033 | W92: =(V92-U92)+1 -> 11
A93: 236204 | B93: 46023 | C93: 46033 | D93: false | E93: 172924 | F93: TEMPORAL. T. COM. INTER. N. ESTA | G93: LIBRE DISPOSICION | H93: TÉCNICA/O AUXILIAR DE FARMACIA | I93: E | J93: S_9B_1AV | K93: S9B1A | L93: 11 | M93: 0 | N93: TÉCNICA/O AUXILIAR DE FARMACIA | O93: ALMACÉN DE FARMACIA | P93: DIRECCIÓN DE ENFERMERÍA | Q93: 360702 | R93: 78859009J | S93: CASTRO FARIÑA, NATALIA | T93: TÉCNICA/O AUXILIAR DE FARMACIA | U93: 46023 | V93: 46033 | W93: =(V93-U93)+1 -> 11
A94: 236228 | B94: 46023 | C94: 46033 | D94: false | E94: 169694 | F94: TEMPORAL. T. COM. INTER. N. ESTA | G94: INTERINO POR VACANTE | H94: FEA HEMATOLOGÍA Y HEMOTERAPIA | I94: E | J94: I_9_1A | K94: N91A | L94: 11 | M94: 0 | N94: FEA HEMATOLOGIA Y HEMOTERAPIA | O94: P.MÉDICO HEMATOLOGÍA CLÍNICA | P94: DIRECCIÓN MÉDICA | Q94: 0 | U94: 46023 | V94: 46033 | W94: =(V94-U94)+1 -> 11
A95: 245994 | B95: 46023 | C95: 46033 | D95: false | E95: 175725 | F95: TEMPORAL. T. PAR. INTERI. N. EST | G95: REDUCCION DE JORNADA | H95: TÉCNICO/A TITULADO/A MEDIO | I95: E | J95: S_9B_1C | K95: S9B1C | L95: 11 | M95: 0 | N95: PERSONAL TÉCNICO (G.MEDIO) | O95: CONSULTA OFTALMOLOGÍA | P95: DIRECCIÓN DE ENFERMERÍA | Q95: 253583 | R95: 78699024Q | S95: FERNANDEZ ALVAREZ, PAULA | T95: PERSONAL TÉCNICO (G.MEDIO) | U95: 46023 | V95: 46033 | W95: =(V95-U95)+1 -> 11
A96: 225280 | B96: 46023 | C96: 46033 | D96: false | E96: 169702 | F96: TEMPORAL. T. COM. INTER. N. ESTA | G96: INTERINO POR VACANTE | H96: FEA MICROBIOLOGÍA Y PARASITOLOGÍA | I96: E | J96: I_9_1A | K96: N91A | L96: 11 | M96: 0 | N96: FEA MICROBIOLOGÍA Y PARASITOLOGÍA | O96: P.MÉDICO MICROBIOLOGÍA Y CONTROL INFECCI | P96: DIRECCIÓN MÉDICA | Q96: 0 | U96: 46023 | V96: 46033 | W96: =(V96-U96)+1 -> 11
A97: 154503 | B97: 46023 | C97: 46033 | D97: false | E97: 168723 | F97: TEMPORAL. T. COMPLETO. N. ESTATU | G97: ACUMULACION DE TAREAS | H97: FEA MEDICINA INTENSIVA | I97: E | J97: I_9_1C | K97: N91C | L97: 11 | M97: 0 | N97: FEA MEDICINA INTENSIVA | O97: P.MÉDICO U.V.I: | P97: DIRECCIÓN MÉDICA | Q97: 0 | U97: 46023 | V97: 46033 | W97: =(V97-U97)+1 -> 11
A98: 249602 | B98: 46028 | C98: 46033 | D98: false | E98: 175636 | F98: TEMPORAL. T. COM. INTER. N. ESTA | G98: MES VENCIDO - INCAPACIDAD TEMPORAL | H98: AUXILIAR DE ENFERMERÍA | I98: E | J98: S_9B_1A | K98: S9B1A | L98: 6 | M98: 0 | N98: AUXILIAR DE ENFERMERÍA | O98: URGENCIAS | P98: DIRECCIÓN DE ENFERMERÍA | Q98: 237692 | R98: 54117767D | S98: CAMPOS GARCIA, ADONAIS JESUS | T98: AUXILIAR DE ENFERMERÍA | U98: 46028 | V98: 46033 | W98: =(V98-U98)+1 -> 6
A99: 345847 | B99: 46032 | C99: 46033 | D99: false | E99: 175837 | F99: TEMPORAL. T. COM. INTER. N. ESTA | G99: LIBRE DISPOSICION | H99: ENFERMERO/A | I99: E | J99: S_9B_1A | K99: S9B1A | L99: 2 | M99: 0 | N99: ENFERMERA/O | O99: URGENCIAS | P99: DIRECCIÓN DE ENFERMERÍA | Q99: 252785 | R99: 21138054L | S99: GONZALEZ RODRIGUEZ, MARTA | T99: ENFERMERA/O | U99: 46032 | V99: 46033 | W99: =(V99-U99)+1 -> 2
A100: 244665 | B100: 46023 | C100: 46034 | D100: false | E100: 175339 | F100: TEMPORAL. T. COM. INTER. N. ESTA | G100: MES VENCIDO - INCAPACIDAD TEMPORAL | H100: AUXILIAR DE ENFERMERÍA | I100: E | J100: S_9B_1A | K100: S9B1A | L100: 12 | M100: 0 | N100: AUXILIAR DE ENFERMERÍA | O100: PLANTILLA VOLANTE | P100: DIRECCIÓN DE ENFERMERÍA | Q100: 206974 | R100: 78558178E | S100: LOPEZ LEDESMA, ELVIRA EUGENIA | T100: AUXILIAR DE ENFERMERÍA | U100: 46023 | V100: 46034 | W100: =(V100-U100)+1 -> 12
A101: 367883 | B101: 46023 | C101: 46034 | D101: false | E101: 174725 | F101: TEMPORAL. T. COM. INTER. N. ESTA | G101: MES VENCIDO - INCAPACIDAD TEMPORAL | H101: AUXILIAR DE ENFERMERÍA | I101: E | J101: S_9B_1A | K101: S9B1A | L101: 12 | M101: 0 | N101: AUXILIAR DE ENFERMERÍA | O101: PLANTA 10ª PAR - HOSP.EDIF.A | P101: DIRECCIÓN DE ENFERMERÍA | Q101: 368874 | R101: 78568483T | S101: GONZALEZ TOSCO, VANESA | T101: AUXILIAR DE ENFERMERÍA | U101: 46023 | V101: 46034 | W101: =(V101-U101)+1 -> 12
A102: 220612 | B102: 46023 | C102: 46034 | D102: false | E102: 174829 | F102: TEMPORAL. T. COM. INTER. N. ESTA | G102: MES VENCIDO - INCAPACIDAD TEMPORAL | H102: ENFERMERO/A | I102: E | J102: S_9B_1A | K102: S9B1A | L102: 12 | M102: 0 | N102: ENFERMERA/O | O102: PLANTA 7ª IMPAR - HOSP.EDIF.A | P102: DIRECCIÓN DE ENFERMERÍA | Q102: 346982 | R102: 31854611W | S102: PIÑERO NAVAS, MARIA LUZ | T102: ENFERMERA/O | U102: 46023 | V102: 46034 | W102: =(V102-U102)+1 -> 12
A103: 298876 | B103: 46023 | C103: 46034 | D103: false | E103: 172617 | F103: TEMPORAL. T. COM. INTER. N. ESTA | G103: MES VENCIDO - INCAPACIDAD TEMPORAL | H103: ENFERMERO/A | I103: E | J103: S_9B_1A | K103: S9B1A | L103: 12 | M103: 0 | N103: ENFERMERA/O | O103: UDAD.ENDOSCOPIA | P103: DIRECCIÓN DE ENFERMERÍA | Q103: 226721 | R103: 43831118H | S103: PIÑERO ORTIZ, MELISSA | T103: ENFERMERA/O | U103: 46023 | V103: 46034 | W103: =(V103-U103)+1 -> 12
A104: 216695 | B104: 46023 | C104: 46034 | D104: false | E104: 173406 | F104: TEMPORAL. T. COM. INTER. N. ESTA | G104: MES VENCIDO - INCAPACIDAD TEMPORAL | H104: LIMPIADOR/A | I104: E | J104: S_9B_1A | K104: S9B1A | L104: 12 | M104: 0 | N104: LIMPIADORA | O104: LIMPIEZA | P104: DIRECCIÓN DE SERVICIOS GENERALES | Q104: 206527 | R104: 54044694F | S104: ROMERO DIAZ, ANTONIO ISMAEL | T104: LIMPIADORA | U104: 46023 | V104: 46034 | W104: =(V104-U104)+1 -> 12
A105: 264835 | B105: 46023 | C105: 46034 | D105: false | E105: 173270 | F105: TEMPORAL. T. COM. INTER. N. ESTA | G105: MES VENCIDO - INCAPACIDAD TEMPORAL | H105: LIMPIADOR/A | I105: E | J105: S_9B_1A | K105: S9B1A | L105: 12 | M105: 0 | N105: LIMPIADORA | O105: LIMPIEZA | P105: DIRECCIÓN DE SERVICIOS GENERALES | Q105: 221908 | R105: 42189104C | S105: HERNANDEZ RODRIGUEZ, DESIREE | T105: LIMPIADORA | U105: 46023 | V105: 46034 | W105: =(V105-U105)+1 -> 12
A106: 311864 | B106: 46023 | C106: 46034 | D106: false | E106: 174474 | F106: TEMPORAL. T. COM. INTER. N. ESTA | G106: VACACIONES Y LIBRANZAS | H106: TELEFONISTA | I106: E | J106: S_9B_1A | K106: S9B1A | L106: 12 | M106: 0 | N106: TELEFONISTA | O106: TELEFONISTAS | P106: DIRECCIÓN DE SERVICIOS GENERALES | Q106: 336709 | R106: 43785467E | S106: SANCHEZ HENRIQUEZ, MACARENA | T106: TELEFONISTA | U106: 46023 | V106: 46034 | W106: =(V106-U106)+1 -> 12
A107: 303100 | B107: 46023 | C107: 46034 | D107: false | E107: 172954 | F107: TEMPORAL. T. COM. INTER. N. ESTA | G107: MES VENCIDO - INCAPACIDAD TEMPORAL | H107: AUXILIAR DE ENFERMERÍA | I107: E | J107: S_9B_1A | K107: S9B1A | L107: 12 | M107: 0 | N107: AUXILIAR DE ENFERMERÍA | O107: PLANTILLA VOLANTE | P107: DIRECCIÓN DE ENFERMERÍA | Q107: 340185 | R107: 45453804P | S107: ENRIQUE RODRIGUEZ, ANSELMA MARIA | T107: AUXILIAR DE ENFERMERÍA | U107: 46023 | V107: 46034 | W107: =(V107-U107)+1 -> 12
A108: 275709 | B108: 46031 | C108: 46034 | D108: false | E108: 174809 | F108: TEMPORAL. T. COM. INTER. N. ESTA | G108: VACACIONES Y LIBRANZAS | H108: CALEFACTOR/A | I108: E | J108: S_9B_1A | K108: S9B1A | L108: 4 | M108: 0 | N108: CALEFACTOR | O108: CALDERAS | P108: DIRECCIÓN DE INGENIERÍA, INFRAESTRUCTURAS Y TEC. | Q108: 232563 | R108: 78696834B | S108: SANTOS DELGADO, JOSUE | T108: CALEFACTOR | U108: 46031 | V108: 46034 | W108: =(V108-U108)+1 -> 4
A109: 247239 | B109: 46032 | C109: 46034 | D109: false | E109: 175746 | F109: TEMPORAL. T. COM. INTER. N. ESTA | G109: LIBRE DISPOSICION | H109: ENFERMERO/A | I109: E | J109: S_9B_1A | K109: S9B1A | L109: 3 | M109: 0 | N109: ENFERMERA/O | O109: DIETÉTICA Y NUTRICIÓN | P109: DIRECCIÓN DE ENFERMERÍA | Q109: 298734 | R109: 43837531Z | S109: GONZALEZ BARRERA, IKER | T109: ENFERMERA/O | U109: 46032 | V109: 46034 | W109: =(V109-U109)+1 -> 3
... A113: 204267 | B113: 46023 | C113: 46035 | D113: false | E113: 169274 | F113: TEMPORAL. T. COM. INTER. N. ESTA | G113: MES VENCIDO - INCAPACIDAD TEMPORAL | H113: AUXILIAR DE ENFERMERÍA | I113: E | J113: S_9B_1A | K113: S9B1A | L113: 13 | M113: 0 | N113: AUXILIAR DE ENFERMERÍA | O113: URGENCIAS | P113: DIRECCIÓN DE ENFERMERÍA | Q113: 238900 | R113: 13137366L | S113: RASTRILLA TERAN, FABIOLA | T113: AUXILIAR DE ENFERMERÍA | U113: 46023 | V113: 46035 | W113: =(V113-U113)+1 -> 13
A114: 399975 | B114: 46023 | C114: 46035 | D114: false | E114: 153000 | F114: TEMPORAL. T. COM. INTER. N. ESTA | G114: INTERINO POR VACANTE | H114: FEA PEDIATRÍA | I114: E | J114: I_9_1A | K114: N91A | L114: 13 | M114: 0 | N114: FEA PEDIATRÍA | O114: P.MÉDICO PEDIATRÍA | P114: DIRECCIÓN MÉDICA | Q114: 0 | U114: 46023 | V114: 46035 | W114: =(V114-U114)+1 -> 13
A115: 257981 | B115: 46023 | C115: 46035 | D115: false | E115: 175501 | F115: TEMPORAL. T. COM. INTER. N. ESTA | G115: MES VENCIDO - INCAPACIDAD TEMPORAL | H115: AUXILIAR DE ENFERMERÍA | I115: E | J115: S_9B_1A | K115: S9B1A | L115: 13 | M115: 0 | N115: AUXILIAR DE ENFERMERÍA | O115: U.V.I. | P115: DIRECCIÓN DE ENFERMERÍA | Q115: 258003 | R115: 54042039C | S115: GONZALEZ SUAREZ, RAQUEL | T115: AUXILIAR DE ENFERMERÍA | U115: 46023 | V115: 46035 | W115: =(V115-U115)+1 -> 13
A116: 262304 | B116: 46023 | C116: 46035 | D116: false | E116: 169553 | F116: TEMPORAL. T. COM. INTER. N. ESTA | G116: MES VENCIDO - INCAPACIDAD TEMPORAL | H116: AUXILIAR DE ENFERMERÍA | I116: E | J116: S_9B_1A | K116: S9B1A | L116: 13 | M116: 0 | N116: AUXILIAR DE ENFERMERÍA | O116: PARITORIO | P116: DIRECCIÓN DE ENFERMERÍA | Q116: 252520 | R116: 42844888M | S116: ORTEGA PERDOMO, ISABEL PILAR | T116: AUXILIAR DE ENFERMERÍA | U116: 46023 | V116: 46035 | W116: =(V116-U116)+1 -> 13
A117: 360031 | B117: 46023 | C117: 46035 | D117: false | E117: 174069 | F117: TEMPORAL. T. COM. INTER. N. ESTA | G117: LIBRE DISPOSICION | H117: AUXILIAR DE ENFERMERÍA | I117: E | J117: S_9B_1AV | K117: S9B1A | L117: 13 | M117: 0 | N117: AUXILIAR DE ENFERMERÍA | O117: DIETÉTICA Y NUTRICIÓN | P117: DIRECCIÓN DE ENFERMERÍA | Q117: 277983 | R117: 42293160R | S117: ESCOBAR SANTILLAN, LOURDES ELIZABETH | T117: AUXILIAR DE ENFERMERÍA | U117: 46023 | V117: 46035 | W117: =(V117-U117)+1 -> 13
A118: 221219 | B118: 46023 | C118: 46035 | D118: false | E118: 174012 | F118: TEMPORAL. T. COM. INTER. N. ESTA | G118: LIBRE DISPOSICION | H118: CELADOR/A | I118: E | J118: S_9B_1AV | K118: S9B1A | L118: 13 | M118: 0 | N118: CELADOR | O118: SUBDIRECCIÓN ENFERMERÍA | P118: DIRECCIÓN DE ENFERMERÍA | Q118: 362667 | R118: 78565180D | S118: VERA GONZALEZ, PEDRO MARTIN | T118: CELADOR | U118: 46023 | V118: 46035 | W118: =(V118-U118)+1 -> 13
A119: 379473 | B119: 46023 | C119: 46035 | D119: false | E119: 168529 | F119: TEMPORAL. T. COMPLETO. N. ESTATU | G119: ACUMULACION DE TAREAS | H119: FEA MEDICINA PREVENTIVA Y SALUD PÚBLICA | I119: E | J119: I_9_1C | K119: N91C | L119: 13 | M119: 0 | N119: FEA MEDICINA PREVENTIVA Y SALUD PÚBLICA | O119: P. MÉDICO PREVENTIVA | P119: DIRECCIÓN MÉDICA | Q119: 0 | U119: 46023 | V119: 46035 | W119: =(V119-U119)+1 -> 13
A120: 343226 | B120: 46023 | C120: 46035 | D120: false | E120: 171963 | F120: TEMPORAL. T. COM. INTER. N. ESTA | G120: MES VENCIDO - INCAPACIDAD TEMPORAL | H120: AUXILIAR DE ENFERMERÍA | I120: E | J120: S_9B_1A | K120: S9B1A | L120: 13 | M120: 0 | N120: AUXILIAR DE ENFERMERÍA | O120: PLANTILLA VOLANTE | P120: DIRECCIÓN DE ENFERMERÍA | Q120: 270447 | R120: 43611550P | S120: ALVAREZ RIGOR, CONCEPCION | T120: AUXILIAR DE ENFERMERÍA | U120: 46023 | V120: 46035 | W120: =(V120-U120)+1 -> 13
A121: 377332 | B121: 46023 | C121: 46035 | D121: false | E121: 171822 | F121: TEMPORAL. T. COM. INTER. N. ESTA | G121: LACTANCIA | H121: AUXILIAR DE ENFERMERÍA | I121: E | J121: S_9B_1A | K121: S9B1A | L121: 13 | M121: 0 | N121: AUXILIAR DE ENFERMERÍA | O121: PLANTILLA VOLANTE | P121: DIRECCIÓN DE ENFERMERÍA | Q121: 265081 | R121: 43385726K | S121: CARBALLO PEREZ, IVANA | T121: AUXILIAR DE ENFERMERÍA | U121: 46023 | V121: 46035 | W121: =(V121-U121)+1 -> 13
A122: 236465 | B122: 46024 | C122: 46035 | D122: false | E122: 175596 | F122: TEMPORAL. T. COM. INTER. N. ESTA | G122: MES VENCIDO - INCAPACIDAD TEMPORAL | H122: AUXILIAR DE ENFERMERÍA | I122: E | J122: S_9B_1A | K122: S9B1A | L122: 12 | M122: 0 | N122: AUXILIAR DE ENFERMERÍA | O122: DIETÉTICA Y NUTRICIÓN | P122: DIRECCIÓN DE ENFERMERÍA | Q122: 277983 | R122: 42293160R | S122: ESCOBAR SANTILLAN, LOURDES ELIZABETH | T122: AUXILIAR DE ENFERMERÍA | U122: 46024 | V122: 46035 | W122: =(V122-U122)+1 -> 12
A123: 213168 | B123: 46035 | C123: 46035 | D123: false | E123: 175841 | F123: TEMPORAL. T. COM. INTER. N. ESTA | G123: MES VENCIDO - INCAPACIDAD TEMPORAL | H123: AUXILIAR DE ENFERMERÍA | I123: E | J123: S_9B_1A | K123: S9B1A | L123: 1 | M123: 0 | N123: AUXILIAR DE ENFERMERÍA | O123: URGENCIAS | P123: DIRECCIÓN DE ENFERMERÍA | Q123: 245836 | R123: 54112837R | S123: URBINA PAEZ, VERUSKA ANDREINA | T123: AUXILIAR DE ENFERMERÍA | U123: 46035 | V123: 46035 | W123: =(V123-U123)+1 -> 1
A124: 264835 | B124: 46035 | C124: 46035 | D124: false | E124: 176159 | F124: TEMPORAL. T. COM. INTER. N. ESTA | G124: LIBRE DISPOSICION | H124: LIMPIADOR/A | I124: E | J124: S_9B_1A | K124: S9B1A | L124: 1 | M124: 0 | N124: LIMPIADORA | O124: LIMPIEZA | P124: DIRECCIÓN DE SERVICIOS GENERALES | Q124: 366414 | R124: 43798933X | S124: ARVELO GONZALEZ, DULCE MARIA | T124: LIMPIADORA | U124: 46035 | V124: 46035 | W124: =(V124-U124)+1 -> 1
A125: 276332 | B125: 46023 | C125: 46036 | D125: false | E125: 175053 | F125: TEMPORAL. T. COM. INTER. N. ESTA | G125: VACACIONES Y LIBRANZAS | H125: LIMPIADOR/A | I125: E | J125: S_9B_1A | K125: S9B1A | L125: 14 | M125: 0 | N125: LIMPIADORA | O125: LIMPIEZA | P125: DIRECCIÓN DE SERVICIOS GENERALES | Q125: 295245 | R125: 78569835H | S125: DELGADO MARTIN, YAIZA | T125: LIMPIADORA | U125: 46023 | V125: 46036 | W125: =(V125-U125)+1 -> 14
A126: 270456 | B126: 46023 | C126: 46036 | D126: false | E126: 175398 | F126: TEMPORAL. T. COM. INTER. N. ESTA | G126: MES VENCIDO - INCAPACIDAD TEMPORAL | H126: ENFERMERO/A | I126: E | J126: S_9B_1A | K126: S9B1A | L126: 14 | M126: 0 | N126: ENFERMERA/O | O126: URGENCIAS | P126: DIRECCIÓN DE ENFERMERÍA | Q126: 249195 | R126: 53586710E | S126: MARQUEZ BERNAL, MARIA JOSE | T126: ENFERMERA/O | U126: 46023 | V126: 46036 | W126: =(V126-U126)+1 -> 14
A127: 264450 | B127: 46023 | C127: 46036 | D127: false | E127: 173942 | F127: TEMPORAL. T. COM. INTER. N. ESTA | G127: LIBRE DISPOSICION | H127: G ADMINISTRATIVO FUNCIÓN ADMINISTRATIVA | I127: E | J127: S_9B_1AV | K127: S9B1A | L127: 14 | M127: 0 | N127: GRUPO ADMINISTRATIVO | O127: ADMISIÓN CENTRAL | P127: DIRECCIÓN MÉDICA | Q127: 208404 | R127: 43348220M | S127: SUAREZ TRUJILLO, MARIA DOLORES | T127: GRUPO ADMINISTRATIVO | U127: 46023 | V127: 46036 | W127: =(V127-U127)+1 -> 14
A128: 246253 | B128: 46031 | C128: 46036 | D128: false | E128: 175682 | F128: TEMPORAL. T. COM. INTER. N. ESTA | G128: MES VENCIDO - INCAPACIDAD TEMPORAL | H128: AUXILIAR DE ENFERMERÍA | I128: E | J128: S_9B_1A | K128: S9B1A | L128: 6 | M128: 0 | N128: AUXILIAR DE ENFERMERÍA | O128: PLANTA 4ª - HOSPITALIZACIÓN EDIF. D | P128: DIRECCIÓN DE ENFERMERÍA | Q128: 337322 | R128: 43784430C | S128: RODRIGUEZ ABREU, ANA ELISA | T128: AUXILIAR DE ENFERMERÍA | U128: 46031 | V128: 46036 | W128: =(V128-U128)+1 -> 6
A129: 296095 | B129: 46031 | C129: 46036 | D129: false | E129: 175675 | F129: TEMPORAL. T. COM. INTER. N. ESTA | G129: MES VENCIDO - INCAPACIDAD TEMPORAL | H129: ENFERMERO/A | I129: E | J129: S_9B_1A | K129: S9B1A | L129: 6 | M129: 0 | N129: ENFERMERA/O | O129: URGENCIAS | P129: DIRECCIÓN DE ENFERMERÍA | Q129: 390987 | R129: 54113558D | S129: GONZALEZ CASTRO, LARA | T129: ENFERMERA/O | U129: 46031 | V129: 46036 | W129: =(V129-U129)+1 -> 6
...

Sheet Panel
B2: PANEL | G2: RESUMEN DE LA BOLSA NETO
B11: =125215+464271 -> 589486 | D11: =ActivosTotales -> 124526.32 | G11: =PasivosTotales -> 462712.01
B12: BOLSA NETO | D12: Bolsa I91c | G12: Bolsa I9B1a
B13: Bolsa I91b | D13: Dirección Planificación y Gestión RREE | G13: Dirección Planificación y Gestión RREE
B14: 32469 | D14: Dirección Enfermería | G14: Dirección Enfermería
D15: Dirección Ingeneria, Infraestrutura y Tecn. | G15: Dirección Ingeneria, Infraestrutura y Tecn.
D16: Dirección Servicios Generales | G16: Dirección Servicios Generales
D17: Dirección Médica | G17: Dirección Médica
D18: Dirección RRHH | G18: Dirección RRHH
D19: Gerencia | G19: Gerencia

Sheet I91b
B2: BOLSA I91b | H2: RESUMEN DE LA BOLSA NETO
D4: BOLSA I91b | E4: Tope | H4: BOLSA I91b | I4: Usados | J4: Resto
D5: Gerencia | E5: =VLOOKUP(tblNoAsegurado10[[#This Row],[BOLSA I91b]],Bolsatotaldirecciones13[#All],2,FALSE) -> 503.2695 | H5: Gerencia | I5: =IFERROR(VLOOKUP(tblAsegurado12[[#This Row],[BOLSA I91b]],Cálculos!$D$14:$F$21,2,FALSE),0) -> 423 | J5: =tblNoAsegurado10[[#This Row],[Tope]]-tblAsegurado12[[#This Row],[Usados]] -> 80.2695
D6: Dirección Médica | E6: =VLOOKUP(tblNoAsegurado10[[#This Row],[BOLSA I91b]],Bolsatotaldirecciones13[#All],2,FALSE) -> 6042.4809 | H6: Dirección Médica | I6: =IFERROR(VLOOKUP(tblAsegurado12[[#This Row],[BOLSA I91b]],Cálculos!$D$14:$F$21,2,FALSE),0) -> 24639 | J6: =tblNoAsegurado10[[#This Row],[Tope]]-tblAsegurado12[[#This Row],[Usados]] -> -18596.519
D7: Dirección Enfermería | E7: =VLOOKUP(tblNoAsegurado10[[#This Row],[BOLSA I91b]],Bolsatotaldirecciones13[#All],2,FALSE) -> 19832.065 | H7: DIRECCIÓN DE ENFERMERÍA | I7: =IFERROR(VLOOKUP(tblAsegurado12[[#This Row],[BOLSA I91b]],Cálculos!$D$14:$F$21,2,FALSE),0) -> 2170 | J7: =tblNoAsegurado10[[#This Row],[Tope]]-tblAsegurado12[[#This Row],[Usados]] -> 17662.065
D8: Dirección Planificación y Gestión RREE | E8: =VLOOKUP(tblNoAsegurado10[[#This Row],[BOLSA I91b]],Bolsatotaldirecciones13[#All],2,FALSE) -> 1883.202 | H8: DIRECCIÓN DE PLANIFIFCACIÓN Y GESTIÓN DE RR.EE. | I8: =IFERROR(VLOOKUP(tblAsegurado12[[#This Row],[BOLSA I91b]],Cálculos!$D$14:$F$21,2,FALSE),0) -> 0 | J8: =tblNoAsegurado10[[#This Row],[Tope]]-tblAsegurado12[[#This Row],[Usados]] -> 1883.202
D9: Dirección Ingenería, Infraestructuras y Tecnologías | E9: =VLOOKUP(tblNoAsegurado10[[#This Row],[BOLSA I91b]],Bolsatotaldirecciones13[#All],2,FALSE) -> 759.7746 | H9: DIRECCIÓN DE INGENIERÍA, INFRAESTRUCTURAS Y TEC. | I9: =IFERROR(VLOOKUP(tblAsegurado12[[#This Row],[BOLSA I91b]],Cálculos!$D$14:$F$21,2,FALSE),0) -> 0 | J9: =tblNoAsegurado10[[#This Row],[Tope]]-tblAsegurado12[[#This Row],[Usados]] -> 759.7746
D10: Dirección Servicios Generales | E10: =VLOOKUP(tblNoAsegurado10[[#This Row],[BOLSA I91b]],Bolsatotaldirecciones13[#All],2,FALSE) -> 2948.1852 | H10: DIRECCIÓN DE SERVICIOS GENERALES | I10: =IFERROR(VLOOKUP(tblAsegurado12[[#This Row],[BOLSA I91b]],Cálculos!$D$14:$F$21,2,FALSE),0) -> 0 | J10: =tblNoAsegurado10[[#This Row],[Tope]]-tblAsegurado12[[#This Row],[Usados]] -> 2948.1852
D11: Dirección RRHH | E11: =VLOOKUP(tblNoAsegurado10[[#This Row],[BOLSA I91b]],Bolsatotaldirecciones13[#All],2,FALSE) -> 496.7757 | H11: DIRECCIÓN DE RR.HH. | I11: =IFERROR(VLOOKUP(tblAsegurado12[[#This Row],[BOLSA I91b]],Cálculos!$D$14:$F$21,2,FALSE),0) -> 735 | J11: =tblNoAsegurado10[[#This Row],[Tope]]-tblAsegurado12[[#This Row],[Usados]] -> -238.2243
B12: =PasivosTotales -> 32465.753 | D12: SUBTOTAL | E12: =SUBTOTAL(109,tblNoAsegurado10[Tope]) -> 32465.753 | H12: SUBTOTAL | I12: =SUBTOTAL(109,tblAsegurado12[Usados]) -> 27967 | J12: =SUBTOTAL(109,tblAsegurado12[Resto]) -> 4498.7531
B14: ACTIVOS TOTALES

Sheet I91c
B2: BOLSA I91c | I2: RESUMEN DE LA BOLSA NETO
D4: Bolsa I91c | E4: Tope | I4: Bolsa I91c | J4: Usados | K4: Resto | L4: Necesidad
D5: Gerencia | E5: 1940.8325 | I5: Gerencia | J5: =VLOOKUP(Bolsausados[[#This Row],[Bolsa I91c]],Cálculos!$D$4:$F$10,2,FALSE) -> 7232 | K5: =Bolsatope[[#This Row],[Tope]]-Bolsausados[[#This Row],[Usados]] -> -5291.1675 | L5: =VLOOKUP(Bolsausados[[#This Row],[Bolsa I91c]],Cálculos!$D$4:$F$10,3,FALSE) -> 0
D6: Dirección Médica | E6: 23289.99 | I6: Dirección Médica | J6: =VLOOKUP(Bolsausados[[#This Row],[Bolsa I91c]],Cálculos!$D$4:$F$10,2,FALSE) -> 37747 | K6: =Bolsatope[[#This Row],[Tope]]-Bolsausados[[#This Row],[Usados]] -> -14457.01 | L6: =VLOOKUP(Bolsausados[[#This Row],[Bolsa I91c]],Cálculos!$D$4:$F$10,3,FALSE) -> 0
D7: Dirección Enfermería | E7: 76506.365 | I7: DIRECCIÓN DE ENFERMERÍA | J7: =VLOOKUP(Bolsausados[[#This Row],[Bolsa I91c]],Cálculos!$D$4:$F$10,2,FALSE) -> 37192 | K7: =Bolsatope[[#This Row],[Tope]]-Bolsausados[[#This Row],[Usados]] -> 39314.365 | L7: =VLOOKUP(Bolsausados[[#This Row],[Bolsa I91c]],Cálculos!$D$4:$F$10,3,FALSE) -> 0
D8: Dirección Planificación y Gestión RREE | E8: 6385.965 | I8: DIRECCIÓN DE PLANIFIFCACIÓN Y GESTIÓN DE RR.EE. | J8: =VLOOKUP(Bolsausados[[#This Row],[Bolsa I91c]],Cálculos!$D$4:$F$10,2,FALSE) -> 4980 | K8: =Bolsatope[[#This Row],[Tope]]-Bolsausados[[#This Row],[Usados]] -> 1405.965 | L8: =VLOOKUP(Bolsausados[[#This Row],[Bolsa I91c]],Cálculos!$D$4:$F$10,3,FALSE) -> 0
D9: Dirección Ingenería, Infraestructuras y Tecnologías | E9: 3005.16 | I9: DIRECCIÓN DE INGENIERÍA, INFRAESTRUCTURAS Y TEC. | J9: =VLOOKUP(Bolsausados[[#This Row],[Bolsa I91c]],Cálculos!$D$4:$F$10,2,FALSE) -> 9919 | K9: =Bolsatope[[#This Row],[Tope]]-Bolsausados[[#This Row],[Usados]] -> -6913.84 | L9: =VLOOKUP(Bolsausados[[#This Row],[Bolsa I91c]],Cálculos!$D$4:$F$10,3,FALSE) -> 0
D10: Dirección Servicios Generales | E10: 11394.565 | I10: DIRECCIÓN DE SERVICIOS GENERALES | J10: =VLOOKUP(Bolsausados[[#This Row],[Bolsa I91c]],Cálculos!$D$4:$F$10,2,FALSE) -> 14054 | K10: =Bolsatope[[#This Row],[Tope]]-Bolsausados[[#This Row],[Usados]] -> -2659.435 | L10: =VLOOKUP(Bolsausados[[#This Row],[Bolsa I91c]],Cálculos!$D$4:$F$10,3,FALSE) -> 0
D11: Dirección RRHH | E11: 2003.44 | I11: DIRECCIÓN DE RR.HH. | J11: =VLOOKUP(Bolsausados[[#This Row],[Bolsa I91c]],Cálculos!$D$4:$F$10,2,FALSE) -> 984 | K11: =Bolsatope[[#This Row],[Tope]]-Bolsausados[[#This Row],[Usados]] -> 1019.44 | L11: =VLOOKUP(Bolsausados[[#This Row],[Bolsa I91c]],Cálculos!$D$4:$F$10,3,FALSE) -> 0
B12: =ActivosTotales -> 124526.32 | D12: SUBTOTAL | E12: =SUBTOTAL(109,Bolsatope[Tope]) -> 124526.32 | I12: SUBTOTAL | J12: =SUBTOTAL(109,Bolsausados[Usados]) -> 112108 | K12: =SUBTOTAL(109,Bolsausados[Resto]) -> 12418.318 | L12: =SUBTOTAL(109,Bolsausados[Necesidad]) -> 0
B14: ACTIVOS TOTALES
D16: INVERSIONES | E16: VALOR | I16: JUBILACIÓN | J16: VALOR
D17: ACCIONES | E17: 15000 | I17: PENSIÓN
D18: BONOS | I18: CUENTAS IRA
D19: INVERSIONES EN FONDOS MUTUOS | I19: CUENTAS KEOGH
D20: PARTICIPACIONES SOCIALES | I20: 401K | J20: 46000
D21: OTRAS INVERSIONES | I21: SEP
I22: ESOP
D23: SUBTOTAL | E23: =SUBTOTAL(109,tblInversiones[VALOR]) -> 15000 | I23: SUBTOTAL | J23: =SUBTOTAL(109,tblJubilación[VALOR]) -> 46000

Sheet I9B1a
B2: BOLSA I9B1a | H2: RESUMEN DE LA BOLSA NETO
D4: BOLSA I9B1a | E4: Tope | H4: BOLSA I9B1a | I4: Usados | J4: Resto
D5: Gerencia | E5: 7211.7005 | H5: Gerencia | I5: =VLOOKUP(tblAsegurado[[#This Row],[BOLSA I9B1a]],Cálculos!$H$4:$I$10,2,FALSE) -> 2829 | J5: =tblNoAsegurado[[#This Row],[Tope]]-tblAsegurado[[#This Row],[Usados]] -> 4382.7005
D6: Dirección Médica | E6: 86540.406 | H6: Dirección Médica | I6: =VLOOKUP(tblAsegurado[[#This Row],[BOLSA I9B1a]],Cálculos!$H$4:$I$10,2,FALSE) -> 18558 | J6: =tblNoAsegurado[[#This Row],[Tope]]-tblAsegurado[[#This Row],[Usados]] -> 67982.406
D7: Dirección Enfermería | E7: 284280.58 | H7: DIRECCIÓN DE ENFERMERÍA | I7: =VLOOKUP(tblAsegurado[[#This Row],[BOLSA I9B1a]],Cálculos!$H$4:$I$10,2,FALSE) -> 261595 | J7: =tblNoAsegurado[[#This Row],[Tope]]-tblAsegurado[[#This Row],[Usados]] -> 22685.581
D8: Dirección Planificación y Gestión RREE | E8: 23728.821 | H8: DIRECCIÓN DE PLANIFIFCACIÓN Y GESTIÓN DE RR.EE. | I8: =VLOOKUP(tblAsegurado[[#This Row],[BOLSA I9B1a]],Cálculos!$H$4:$I$10,2,FALSE) -> 23579 | J8: =tblNoAsegurado[[#This Row],[Tope]]-tblAsegurado[[#This Row],[Usados]] -> 149.821
D9: Dirección Ingenería, Infraestructuras y Tecnologías | E9: 11166.504 | H9: DIRECCIÓN DE INGENIERÍA, INFRAESTRUCTURAS Y TEC. | I9: =VLOOKUP(tblAsegurado[[#This Row],[BOLSA I9B1a]],Cálculos!$H$4:$I$10,2,FALSE) -> 8879 | J9: =tblNoAsegurado[[#This Row],[Tope]]-tblAsegurado[[#This Row],[Usados]] -> 2287.504
D10: Dirección Servicios Generales | E10: 42339.661 | H10: DIRECCIÓN DE SERVICIOS GENERALES | I10: =VLOOKUP(tblAsegurado[[#This Row],[BOLSA I9B1a]],Cálculos!$H$4:$I$10,2,FALSE) -> 50799 | J10: =tblNoAsegurado[[#This Row],[Tope]]-tblAsegurado[[#This Row],[Usados]] -> -8459.339
D11: Dirección RRHH | E11: 7444.336 | H11: DIRECCIÓN DE RR.HH. | I11: =VLOOKUP(tblAsegurado[[#This Row],[BOLSA I9B1a]],Cálculos!$H$4:$I$10,2,FALSE) -> 4504 | J11: =tblNoAsegurado[[#This Row],[Tope]]-tblAsegurado[[#This Row],[Usados]] -> 2940.336
B12: =PasivosTotales -> 462712.01 | D12: SUBTOTAL | E12: =SUBTOTAL(109,tblNoAsegurado[Tope]) -> 462712.01 | H12: SUBTOTAL | I12: =SUBTOTAL(109,tblAsegurado[Usados]) -> 370743 | J12: =SUBTOTAL(109,tblAsegurado[Resto]) -> 91969.01
B14: ACTIVOS TOTALES

Sheet Cálculos
A1: Bolsa N91C | B1: Tope | D1: T.Nombrto | E1: N91C | H1: T.Nombrto | I1: S9B1A
A2: Gerencia | B2: 1940.8325
A3: Dirección Médica | B3: 23289.99 | D3: Etiquetas de fila | E3: Suma de Días | F3: Suma de Días-N | H3: Etiquetas de fila | I3: Suma de Días
A4: Dirección Enfermería | B4: 76506.365 | D4: DIRECCIÓN DE ENFERMERÍA | E4: 37192 | F4: 0 | H4: DIRECCIÓN DE ENFERMERÍA | I4: 261595
A5: Dirección Planificación y Gestión RREE | B5: 6385.965 | D5: DIRECCIÓN DE INGENIERÍA, INFRAESTRUCTURAS Y TEC. | E5: 9919 | F5: 0 | H5: DIRECCIÓN DE INGENIERÍA, INFRAESTRUCTURAS Y TEC. | I5: 8879
A6: Dirección Ingenería, Infraestructuras y Tecnologías | B6: 3005.16 | D6: DIRECCIÓN DE PLANIFIFCACIÓN Y GESTIÓN DE RR.EE. | E6: 4980 | F6: 0 | H6: DIRECCIÓN DE PLANIFIFCACIÓN Y GESTIÓN DE RR.EE. | I6: 23579
A7: Dirección Servicios Generales | B7: 11394.565 | D7: DIRECCIÓN DE RR.HH. | E7: 984 | F7: 0 | H7: DIRECCIÓN DE RR.HH. | I7: 4504
A8: Dirección RRHH | B8: 2003.44 | D8: DIRECCIÓN DE SERVICIOS GENERALES | E8: 14054 | F8: 0 | H8: DIRECCIÓN DE SERVICIOS GENERALES | I8: 50799
A9: SUBTOTAL | B9: 124526.32 | D9: DIRECCIÓN MÉDICA | E9: 37747 | F9: 0 | H9: DIRECCIÓN MÉDICA | I9: 18558
D10: GERENCIA | E10: 7232 | F10: 0 | H10: GERENCIA | I10: 2829
D11: Total general | E11: 112108 | F11: 0 | H11: Total general | I11: 370743
A14: Bolsa N91b | B14: Tope | D14: T.Nombrto | E14: N91B
A15: Gerencia | B15: =$B$26*B35/100 -> 503.2695
A16: Dirección Médica | B16: =$B$26*B36/100 -> 6042.4809 | D16: Etiquetas de fila | E16: Suma de Días | F16: Suma de Días-N
A17: Dirección Enfermería | B17: =$B$26*B37/100 -> 19832.065 | D17: DIRECCIÓN DE ENFERMERÍA | E17: 2170 | F17: 0
A18: Dirección Planificación y Gestión RREE | B18: =$B$26*B38/100 -> 1883.202 | D18: DIRECCIÓN DE RR.HH. | E18: 735 | F18: 0
A19: Dirección Ingenería, Infraestructuras y Tecnologías | B19: =$B$26*B39/100 -> 759.7746 | D19: DIRECCIÓN MÉDICA | E19: 24639 | F19: 0
A20: Dirección Servicios Generales | B20: =$B$26*B40/100 -> 2948.1852 | D20: GERENCIA | E20: 423 | F20: 0
A21: Dirección RRHH | B21: =$B$26*B41/100 -> 496.7757 | D21: Total general | E21: 27967 | F21: 0
A22: SUBTOTAL | B22: =SUBTOTAL(109,B15:B21) -> 32465.753
A25: Bolsas | B25: Tope
A26: I91b | B26: 32469
A27: I91c | B27: 125215
A28: I9B1a | B28: 465271
A29: I9B1b | B29: 64
A30: I9B1c | B30: 0
A31: SUBTOTAL | B31: =SUBTOTAL(109,B26:B30) -> 623019
A34: Ponderación PO Estatutario | B34: %
A35: Gerencia | B35: 1.55
A36: Dirección Médica | B36: 18.61
A37: Dirección Enfermería | B37: 61.08
A38: Dirección Planificación y Gestión RREE | B38: 5.8
A39: Dirección Ingenería, Infraestructuras y Tecnologías | B39: 2.34
A40: Dirección Servicios Generales | B40: 9.08
A41: Dirección RRHH | B41: 1.53
A42: SUBTOTAL | B42: =SUBTOTAL(109,B35:B41) -> 99.99
